[
    {
        "timestamp":1731628800000,
        "price":8.59704772,
        "date":"2024-11-15T00:00:00.000"
    },
    {
        "timestamp":1731715200000,
        "price":8.8715659,
        "date":"2024-11-16T00:00:00.000"
    },
    {
        "timestamp":1731801600000,
        "price":9.24829939,
        "date":"2024-11-17T00:00:00.000"
    },
    {
        "timestamp":1731888000000,
        "price":8.97977984,
        "date":"2024-11-18T00:00:00.000"
    },
    {
        "timestamp":1731974400000,
        "price":9.47045823,
        "date":"2024-11-19T00:00:00.000"
    },
    {
        "timestamp":1732060800000,
        "price":9.39744516,
        "date":"2024-11-20T00:00:00.000"
    },
    {
        "timestamp":1732147200000,
        "price":8.48850089,
        "date":"2024-11-21T00:00:00.000"
    },
    {
        "timestamp":1732233600000,
        "price":8.56144886,
        "date":"2024-11-22T00:00:00.000"
    },
    {
        "timestamp":1732320000000,
        "price":8.40643533,
        "date":"2024-11-23T00:00:00.000"
    },
    {
        "timestamp":1732406400000,
        "price":8.43364713,
        "date":"2024-11-24T00:00:00.000"
    },
    {
        "timestamp":1732492800000,
        "price":8.55461044,
        "date":"2024-11-25T00:00:00.000"
    },
    {
        "timestamp":1732579200000,
        "price":8.23831248,
        "date":"2024-11-26T00:00:00.000"
    },
    {
        "timestamp":1732665600000,
        "price":8.0573341,
        "date":"2024-11-27T00:00:00.000"
    },
    {
        "timestamp":1732752000000,
        "price":8.55283733,
        "date":"2024-11-28T00:00:00.000"
    },
    {
        "timestamp":1732838400000,
        "price":8.64385309,
        "date":"2024-11-29T00:00:00.000"
    },
    {
        "timestamp":1732924800000,
        "price":8.94405095,
        "date":"2024-11-30T00:00:00.000"
    },
    {
        "timestamp":1733011200000,
        "price":9.18903729,
        "date":"2024-12-01T00:00:00.000"
    },
    {
        "timestamp":1733097600000,
        "price":9.51803339,
        "date":"2024-12-02T00:00:00.000"
    },
    {
        "timestamp":1733184000000,
        "price":9.91349773,
        "date":"2024-12-03T00:00:00.000"
    },
    {
        "timestamp":1733270400000,
        "price":10.6080649,
        "date":"2024-12-04T00:00:00.000"
    },
    {
        "timestamp":1733356800000,
        "price":10.84593846,
        "date":"2024-12-05T00:00:00.000"
    },
    {
        "timestamp":1733443200000,
        "price":10.5813234,
        "date":"2024-12-06T00:00:00.000"
    },
    {
        "timestamp":1733529600000,
        "price":11.06175637,
        "date":"2024-12-07T00:00:00.000"
    },
    {
        "timestamp":1733616000000,
        "price":10.95095076,
        "date":"2024-12-08T00:00:00.000"
    },
    {
        "timestamp":1733702400000,
        "price":11.42973972,
        "date":"2024-12-09T00:00:00.000"
    },
    {
        "timestamp":1733788800000,
        "price":9.63007848,
        "date":"2024-12-10T00:00:00.000"
    },
    {
        "timestamp":1733875200000,
        "price":9.54667928,
        "date":"2024-12-11T00:00:00.000"
    },
    {
        "timestamp":1733961600000,
        "price":9.55448514,
        "date":"2024-12-12T00:00:00.000"
    },
    {
        "timestamp":1734048000000,
        "price":9.84704957,
        "date":"2024-12-13T00:00:00.000"
    },
    {
        "timestamp":1734134400000,
        "price":10.07772125,
        "date":"2024-12-14T00:00:00.000"
    },
    {
        "timestamp":1734220800000,
        "price":9.55854795,
        "date":"2024-12-15T00:00:00.000"
    },
    {
        "timestamp":1734307200000,
        "price":8.54642523,
        "date":"2024-12-16T00:00:00.000"
    },
    {
        "timestamp":1734393600000,
        "price":7.38283341,
        "date":"2024-12-17T00:00:00.000"
    },
    {
        "timestamp":1734480000000,
        "price":8.16244812,
        "date":"2024-12-18T00:00:00.000"
    },
    {
        "timestamp":1734566400000,
        "price":7.53067205,
        "date":"2024-12-19T00:00:00.000"
    },
    {
        "timestamp":1734652800000,
        "price":8.38059099,
        "date":"2024-12-20T00:00:00.000"
    },
    {
        "timestamp":1734739200000,
        "price":9.16934648,
        "date":"2024-12-21T00:00:00.000"
    },
    {
        "timestamp":1734825600000,
        "price":9.75903035,
        "date":"2024-12-22T00:00:00.000"
    },
    {
        "timestamp":1734912000000,
        "price":10.04061113,
        "date":"2024-12-23T00:00:00.000"
    },
    {
        "timestamp":1734998400000,
        "price":13.00195758,
        "date":"2024-12-24T00:00:00.000"
    },
    {
        "timestamp":1735084800000,
        "price":14.92321638,
        "date":"2024-12-25T00:00:00.000"
    },
    {
        "timestamp":1735171200000,
        "price":13.45284669,
        "date":"2024-12-26T00:00:00.000"
    },
    {
        "timestamp":1735257600000,
        "price":13.37656498,
        "date":"2024-12-27T00:00:00.000"
    },
    {
        "timestamp":1735344000000,
        "price":12.23185581,
        "date":"2024-12-28T00:00:00.000"
    },
    {
        "timestamp":1735430400000,
        "price":12.91818957,
        "date":"2024-12-29T00:00:00.000"
    },
    {
        "timestamp":1735516800000,
        "price":12.55526117,
        "date":"2024-12-30T00:00:00.000"
    },
    {
        "timestamp":1735603200000,
        "price":14.3230868,
        "date":"2024-12-31T00:00:00.000"
    },
    {
        "timestamp":1735689600000,
        "price":14.9227763,
        "date":"2025-01-01T00:00:00.000"
    },
    {
        "timestamp":1735776000000,
        "price":14.97835784,
        "date":"2025-01-02T00:00:00.000"
    },
    {
        "timestamp":1735862400000,
        "price":19.75263454,
        "date":"2025-01-03T00:00:00.000"
    },
    {
        "timestamp":1735948800000,
        "price":18.62122062,
        "date":"2025-01-04T00:00:00.000"
    },
    {
        "timestamp":1736035200000,
        "price":17.19958267,
        "date":"2025-01-05T00:00:00.000"
    },
    {
        "timestamp":1736121600000,
        "price":16.98809782,
        "date":"2025-01-06T00:00:00.000"
    },
    {
        "timestamp":1736208000000,
        "price":16.12009946,
        "date":"2025-01-07T00:00:00.000"
    },
    {
        "timestamp":1736294400000,
        "price":15.41128254,
        "date":"2025-01-08T00:00:00.000"
    },
    {
        "timestamp":1736380800000,
        "price":14.95465706,
        "date":"2025-01-09T00:00:00.000"
    },
    {
        "timestamp":1736467200000,
        "price":14.71879859,
        "date":"2025-01-10T00:00:00.000"
    },
    {
        "timestamp":1736553600000,
        "price":14.94101626,
        "date":"2025-01-11T00:00:00.000"
    },
    {
        "timestamp":1736640000000,
        "price":15.95600842,
        "date":"2025-01-12T00:00:00.000"
    },
    {
        "timestamp":1736726400000,
        "price":16.14255076,
        "date":"2025-01-13T00:00:00.000"
    },
    {
        "timestamp":1736812800000,
        "price":13.68360772,
        "date":"2025-01-14T00:00:00.000"
    },
    {
        "timestamp":1736899200000,
        "price":16.98657561,
        "date":"2025-01-15T00:00:00.000"
    },
    {
        "timestamp":1736985600000,
        "price":17.93102839,
        "date":"2025-01-16T00:00:00.000"
    },
    {
        "timestamp":1737072000000,
        "price":16.40858631,
        "date":"2025-01-17T00:00:00.000"
    },
    {
        "timestamp":1737158400000,
        "price":16.95874874,
        "date":"2025-01-18T00:00:00.000"
    },
    {
        "timestamp":1737244800000,
        "price":17.47217797,
        "date":"2025-01-19T00:00:00.000"
    },
    {
        "timestamp":1737331200000,
        "price":17.52421212,
        "date":"2025-01-20T00:00:00.000"
    },
    {
        "timestamp":1737417600000,
        "price":18.71682196,
        "date":"2025-01-21T00:00:00.000"
    },
    {
        "timestamp":1737504000000,
        "price":19.59228597,
        "date":"2025-01-22T00:00:00.000"
    },
    {
        "timestamp":1737590400000,
        "price":19.55563394,
        "date":"2025-01-23T00:00:00.000"
    },
    {
        "timestamp":1737676800000,
        "price":19.43663356,
        "date":"2025-01-24T00:00:00.000"
    },
    {
        "timestamp":1737763200000,
        "price":18.59587107,
        "date":"2025-01-25T00:00:00.000"
    },
    {
        "timestamp":1737849600000,
        "price":19.53971525,
        "date":"2025-01-26T00:00:00.000"
    },
    {
        "timestamp":1737936000000,
        "price":19.6082108,
        "date":"2025-01-27T00:00:00.000"
    },
    {
        "timestamp":1738022400000,
        "price":21.43510236,
        "date":"2025-01-28T00:00:00.000"
    },
    {
        "timestamp":1738108800000,
        "price":19.48336981,
        "date":"2025-01-29T00:00:00.000"
    },
    {
        "timestamp":1738195200000,
        "price":16.19361689,
        "date":"2025-01-30T00:00:00.000"
    },
    {
        "timestamp":1738281600000,
        "price":21.0006497,
        "date":"2025-01-31T00:00:00.000"
    },
    {
        "timestamp":1738368000000,
        "price":21.55448293,
        "date":"2025-02-01T00:00:00.000"
    },
    {
        "timestamp":1738454400000,
        "price":20.88582713,
        "date":"2025-02-02T00:00:00.000"
    },
    {
        "timestamp":1738540800000,
        "price":20.23817313,
        "date":"2025-02-03T00:00:00.000"
    },
    {
        "timestamp":1738627200000,
        "price":23.87997563,
        "date":"2025-02-04T00:00:00.000"
    },
    {
        "timestamp":1738713600000,
        "price":20.99835433,
        "date":"2025-02-05T00:00:00.000"
    },
    {
        "timestamp":1738800000000,
        "price":20.72172317,
        "date":"2025-02-06T00:00:00.000"
    },
    {
        "timestamp":1738886400000,
        "price":20.25009004,
        "date":"2025-02-07T00:00:00.000"
    },
    {
        "timestamp":1738972800000,
        "price":20.61296341,
        "date":"2025-02-08T00:00:00.000"
    },
    {
        "timestamp":1739059200000,
        "price":20.07910333,
        "date":"2025-02-09T00:00:00.000"
    },
    {
        "timestamp":1739145600000,
        "price":19.58062037,
        "date":"2025-02-10T00:00:00.000"
    },
    {
        "timestamp":1739232000000,
        "price":19.37168367,
        "date":"2025-02-11T00:00:00.000"
    },
    {
        "timestamp":1739318400000,
        "price":19.08821197,
        "date":"2025-02-12T00:00:00.000"
    },
    {
        "timestamp":1739378438000,
        "price":17.80550963,
        "date":"2025-02-12T16:40:38.000"
    }
]