[
    {
        "timestamp":1732924800000,
        "price":6.98465141,
        "date":"2024-11-30T00:00:00.000"
    },
    {
        "timestamp":1733011200000,
        "price":7.01287195,
        "date":"2024-12-01T00:00:00.000"
    },
    {
        "timestamp":1733097600000,
        "price":6.92756728,
        "date":"2024-12-02T00:00:00.000"
    },
    {
        "timestamp":1733184000000,
        "price":7.41814229,
        "date":"2024-12-03T00:00:00.000"
    },
    {
        "timestamp":1733270400000,
        "price":7.37744982,
        "date":"2024-12-04T00:00:00.000"
    },
    {
        "timestamp":1733356800000,
        "price":7.46833105,
        "date":"2024-12-05T00:00:00.000"
    },
    {
        "timestamp":1733443200000,
        "price":7.66368878,
        "date":"2024-12-06T00:00:00.000"
    },
    {
        "timestamp":1733529600000,
        "price":8.02407153,
        "date":"2024-12-07T00:00:00.000"
    },
    {
        "timestamp":1733616000000,
        "price":7.76420936,
        "date":"2024-12-08T00:00:00.000"
    },
    {
        "timestamp":1733702400000,
        "price":7.87907494,
        "date":"2024-12-09T00:00:00.000"
    },
    {
        "timestamp":1733788800000,
        "price":6.53040437,
        "date":"2024-12-10T00:00:00.000"
    },
    {
        "timestamp":1733875200000,
        "price":6.42610906,
        "date":"2024-12-11T00:00:00.000"
    },
    {
        "timestamp":1733961600000,
        "price":6.83934714,
        "date":"2024-12-12T00:00:00.000"
    },
    {
        "timestamp":1734048000000,
        "price":6.89915301,
        "date":"2024-12-13T00:00:00.000"
    },
    {
        "timestamp":1734134400000,
        "price":6.88206085,
        "date":"2024-12-14T00:00:00.000"
    },
    {
        "timestamp":1734220800000,
        "price":6.68054254,
        "date":"2024-12-15T00:00:00.000"
    },
    {
        "timestamp":1734307200000,
        "price":6.8832187,
        "date":"2024-12-16T00:00:00.000"
    },
    {
        "timestamp":1734393600000,
        "price":6.62650583,
        "date":"2024-12-17T00:00:00.000"
    },
    {
        "timestamp":1734480000000,
        "price":6.37281483,
        "date":"2024-12-18T00:00:00.000"
    },
    {
        "timestamp":1734566400000,
        "price":5.70566452,
        "date":"2024-12-19T00:00:00.000"
    },
    {
        "timestamp":1734652800000,
        "price":5.23287122,
        "date":"2024-12-20T00:00:00.000"
    },
    {
        "timestamp":1734739200000,
        "price":5.34610982,
        "date":"2024-12-21T00:00:00.000"
    },
    {
        "timestamp":1734825600000,
        "price":5.00690987,
        "date":"2024-12-22T00:00:00.000"
    },
    {
        "timestamp":1734912000000,
        "price":5.02851725,
        "date":"2024-12-23T00:00:00.000"
    },
    {
        "timestamp":1734998400000,
        "price":5.42620379,
        "date":"2024-12-24T00:00:00.000"
    },
    {
        "timestamp":1735084800000,
        "price":5.55724934,
        "date":"2024-12-25T00:00:00.000"
    },
    {
        "timestamp":1735171200000,
        "price":5.44013506,
        "date":"2024-12-26T00:00:00.000"
    },
    {
        "timestamp":1735257600000,
        "price":5.08414015,
        "date":"2024-12-27T00:00:00.000"
    },
    {
        "timestamp":1735344000000,
        "price":5.10594697,
        "date":"2024-12-28T00:00:00.000"
    },
    {
        "timestamp":1735430400000,
        "price":5.32371954,
        "date":"2024-12-29T00:00:00.000"
    },
    {
        "timestamp":1735516800000,
        "price":5.13135857,
        "date":"2024-12-30T00:00:00.000"
    },
    {
        "timestamp":1735603200000,
        "price":5.03103164,
        "date":"2024-12-31T00:00:00.000"
    },
    {
        "timestamp":1735689600000,
        "price":4.90576552,
        "date":"2025-01-01T00:00:00.000"
    },
    {
        "timestamp":1735776000000,
        "price":5.27563844,
        "date":"2025-01-02T00:00:00.000"
    },
    {
        "timestamp":1735862400000,
        "price":5.43040495,
        "date":"2025-01-03T00:00:00.000"
    },
    {
        "timestamp":1735948800000,
        "price":5.79326341,
        "date":"2025-01-04T00:00:00.000"
    },
    {
        "timestamp":1736035200000,
        "price":5.79628679,
        "date":"2025-01-05T00:00:00.000"
    },
    {
        "timestamp":1736121600000,
        "price":5.91034805,
        "date":"2025-01-06T00:00:00.000"
    },
    {
        "timestamp":1736208000000,
        "price":6.00076838,
        "date":"2025-01-07T00:00:00.000"
    },
    {
        "timestamp":1736294400000,
        "price":5.38163386,
        "date":"2025-01-08T00:00:00.000"
    },
    {
        "timestamp":1736380800000,
        "price":5.15712167,
        "date":"2025-01-09T00:00:00.000"
    },
    {
        "timestamp":1736467200000,
        "price":4.9800859,
        "date":"2025-01-10T00:00:00.000"
    },
    {
        "timestamp":1736553600000,
        "price":5.08602695,
        "date":"2025-01-11T00:00:00.000"
    },
    {
        "timestamp":1736640000000,
        "price":5.08448304,
        "date":"2025-01-12T00:00:00.000"
    },
    {
        "timestamp":1736726400000,
        "price":4.9681584,
        "date":"2025-01-13T00:00:00.000"
    },
    {
        "timestamp":1736812800000,
        "price":4.75353965,
        "date":"2025-01-14T00:00:00.000"
    },
    {
        "timestamp":1736899200000,
        "price":5.04415171,
        "date":"2025-01-15T00:00:00.000"
    },
    {
        "timestamp":1736985600000,
        "price":5.31954655,
        "date":"2025-01-16T00:00:00.000"
    },
    {
        "timestamp":1737072000000,
        "price":5.16167595,
        "date":"2025-01-17T00:00:00.000"
    },
    {
        "timestamp":1737158400000,
        "price":5.75696309,
        "date":"2025-01-18T00:00:00.000"
    },
    {
        "timestamp":1737244800000,
        "price":5.45649968,
        "date":"2025-01-19T00:00:00.000"
    },
    {
        "timestamp":1737331200000,
        "price":4.97666135,
        "date":"2025-01-20T00:00:00.000"
    },
    {
        "timestamp":1737417600000,
        "price":5.07873172,
        "date":"2025-01-21T00:00:00.000"
    },
    {
        "timestamp":1737504000000,
        "price":5.251907,
        "date":"2025-01-22T00:00:00.000"
    },
    {
        "timestamp":1737590400000,
        "price":5.08697868,
        "date":"2025-01-23T00:00:00.000"
    },
    {
        "timestamp":1737676800000,
        "price":4.98767779,
        "date":"2025-01-24T00:00:00.000"
    },
    {
        "timestamp":1737763200000,
        "price":4.99008377,
        "date":"2025-01-25T00:00:00.000"
    },
    {
        "timestamp":1737849600000,
        "price":4.94047947,
        "date":"2025-01-26T00:00:00.000"
    },
    {
        "timestamp":1737936000000,
        "price":4.7582211,
        "date":"2025-01-27T00:00:00.000"
    },
    {
        "timestamp":1738022400000,
        "price":4.62701255,
        "date":"2025-01-28T00:00:00.000"
    },
    {
        "timestamp":1738108800000,
        "price":4.28325297,
        "date":"2025-01-29T00:00:00.000"
    },
    {
        "timestamp":1738195200000,
        "price":4.41315403,
        "date":"2025-01-30T00:00:00.000"
    },
    {
        "timestamp":1738281600000,
        "price":4.60466344,
        "date":"2025-01-31T00:00:00.000"
    },
    {
        "timestamp":1738368000000,
        "price":4.61557088,
        "date":"2025-02-01T00:00:00.000"
    },
    {
        "timestamp":1738454400000,
        "price":4.27163349,
        "date":"2025-02-02T00:00:00.000"
    },
    {
        "timestamp":1738540800000,
        "price":3.72230758,
        "date":"2025-02-03T00:00:00.000"
    },
    {
        "timestamp":1738627200000,
        "price":3.7652795,
        "date":"2025-02-04T00:00:00.000"
    },
    {
        "timestamp":1738713600000,
        "price":3.41229578,
        "date":"2025-02-05T00:00:00.000"
    },
    {
        "timestamp":1738800000000,
        "price":3.28263713,
        "date":"2025-02-06T00:00:00.000"
    },
    {
        "timestamp":1738886400000,
        "price":3.14495003,
        "date":"2025-02-07T00:00:00.000"
    },
    {
        "timestamp":1738972800000,
        "price":3.19878384,
        "date":"2025-02-08T00:00:00.000"
    },
    {
        "timestamp":1739059200000,
        "price":3.28898655,
        "date":"2025-02-09T00:00:00.000"
    },
    {
        "timestamp":1739145600000,
        "price":3.18376043,
        "date":"2025-02-10T00:00:00.000"
    },
    {
        "timestamp":1739232000000,
        "price":3.20174339,
        "date":"2025-02-11T00:00:00.000"
    },
    {
        "timestamp":1739318400000,
        "price":3.20423545,
        "date":"2025-02-12T00:00:00.000"
    },
    {
        "timestamp":1739404800000,
        "price":3.4262213,
        "date":"2025-02-13T00:00:00.000"
    },
    {
        "timestamp":1739491200000,
        "price":3.37158228,
        "date":"2025-02-14T00:00:00.000"
    },
    {
        "timestamp":1739577600000,
        "price":3.5476878,
        "date":"2025-02-15T00:00:00.000"
    },
    {
        "timestamp":1739664000000,
        "price":3.40583665,
        "date":"2025-02-16T00:00:00.000"
    },
    {
        "timestamp":1739750400000,
        "price":3.41611768,
        "date":"2025-02-17T00:00:00.000"
    },
    {
        "timestamp":1739836800000,
        "price":3.25398847,
        "date":"2025-02-18T00:00:00.000"
    },
    {
        "timestamp":1739923200000,
        "price":3.13216642,
        "date":"2025-02-19T00:00:00.000"
    },
    {
        "timestamp":1740009600000,
        "price":3.15578205,
        "date":"2025-02-20T00:00:00.000"
    },
    {
        "timestamp":1740096000000,
        "price":3.46922791,
        "date":"2025-02-21T00:00:00.000"
    },
    {
        "timestamp":1740182400000,
        "price":3.30612914,
        "date":"2025-02-22T00:00:00.000"
    },
    {
        "timestamp":1740268800000,
        "price":3.47513245,
        "date":"2025-02-23T00:00:00.000"
    },
    {
        "timestamp":1740355200000,
        "price":3.42780875,
        "date":"2025-02-24T00:00:00.000"
    },
    {
        "timestamp":1740441600000,
        "price":3.05639613,
        "date":"2025-02-25T00:00:00.000"
    },
    {
        "timestamp":1740528000000,
        "price":3.00489591,
        "date":"2025-02-26T00:00:00.000"
    },
    {
        "timestamp":1740614400000,
        "price":3.00396003,
        "date":"2025-02-27T00:00:00.000"
    },
    {
        "timestamp":1740652253000,
        "price":3.13247684,
        "date":"2025-02-27T10:30:53.000"
    }
]