[
    {
        "id": "bitcoin",
        "symbol": "btc",
        "name": "Bitcoin",
        "image": "https://coin-images.coingecko.com/coins/images/1/large/bitcoin.png?1696501400",
        "current_price": 79469,
        "market_cap": 1574116030456,
        "market_cap_rank": 1,
        "fully_diluted_valuation": 1574116030456,
        "total_volume": 92114477521,
        "high_24h": 82704,
        "low_24h": 74604,
        "price_change_24h": -3114.385018321089,
        "price_change_percentage_24h": -3.77121,
        "market_cap_change_24h": -65503853698.65747,
        "market_cap_change_percentage_24h": -3.99506,
        "circulating_supply": 19847978.0,
        "total_supply": 19847978.0,
        "max_supply": 21000000.0,
        "ath": 108786,
        "ath_change_percentage": -28.02422,
        "ath_date": "2025-01-20T09:11:54.494Z",
        "atl": 67.81,
        "atl_change_percentage": 115370.26986,
        "atl_date": "2013-07-06T00:00:00.000Z",
        "roi": null,
        "last_updated": "2025-04-07T14:56:25.601Z"
    },
    {
        "id": "ethereum",
        "symbol": "eth",
        "name": "Ethereum",
        "image": "https://coin-images.coingecko.com/coins/images/279/large/ethereum.png?1696501628",
        "current_price": 1575.15,
        "market_cap": 189655624869,
        "market_cap_rank": 2,
        "fully_diluted_valuation": 189655624869,
        "total_volume": 55339869026,
        "high_24h": 1769.96,
        "low_24h": 1431.73,
        "price_change_24h": -190.479598686519,
        "price_change_percentage_24h": -10.78822,
        "market_cap_change_24h": -23274904595.454437,
        "market_cap_change_percentage_24h": -10.93075,
        "circulating_supply": 120674307.3057722,
        "total_supply": 120674307.3057722,
        "max_supply": null,
        "ath": 4878.26,
        "ath_change_percentage": -68.07214,
        "ath_date": "2021-11-10T14:24:19.604Z",
        "atl": 0.432979,
        "atl_change_percentage": 359622.92082,
        "atl_date": "2015-10-20T00:00:00.000Z",
        "roi": {
            "times": 25.53854475993121,
            "currency": "btc",
            "percentage": 2553.854475993121
        },
        "last_updated": "2025-04-07T14:56:29.014Z"
    },
    {
        "id": "binancecoin",
        "symbol": "bnb",
        "name": "BNB",
        "image": "https://coin-images.coingecko.com/coins/images/825/large/bnb-icon2_2x.png?1696501970",
        "current_price": 558.2,
        "market_cap": 81245040772,
        "market_cap_rank": 5,
        "fully_diluted_valuation": 81245040772,
        "total_volume": 2492252914,
        "high_24h": 582.59,
        "low_24h": 523.38,
        "price_change_24h": -24.38827497036482,
        "price_change_percentage_24h": -4.1862,
        "market_cap_change_24h": -3723730957.2678833,
        "market_cap_change_percentage_24h": -4.38247,
        "circulating_supply": 145887575.79,
        "total_supply": 145887575.79,
        "max_supply": 200000000.0,
        "ath": 788.84,
        "ath_change_percentage": -29.98223,
        "ath_date": "2024-12-04T10:35:25.220Z",
        "atl": 0.0398177,
        "atl_change_percentage": 1387048.78465,
        "atl_date": "2017-10-19T00:00:00.000Z",
        "roi": null,
        "last_updated": "2025-04-07T14:56:24.550Z"
    },
    {
        "id": "solana",
        "symbol": "sol",
        "name": "Solana",
        "image": "https://coin-images.coingecko.com/coins/images/4128/large/solana.png?1718769756",
        "current_price": 107.7,
        "market_cap": 55379278612,
        "market_cap_rank": 7,
        "fully_diluted_valuation": 64243709657,
        "total_volume": 10594482537,
        "high_24h": 115.52,
        "low_24h": 96.7,
        "price_change_24h": -7.571989109015945,
        "price_change_percentage_24h": -6.56875,
        "market_cap_change_24h": -3892251395.5512238,
        "market_cap_change_percentage_24h": -6.56681,
        "circulating_supply": 515473945.3082142,
        "total_supply": 597984648.9248978,
        "max_supply": null,
        "ath": 293.31,
        "ath_change_percentage": -63.9558,
        "ath_date": "2025-01-19T11:15:27.957Z",
        "atl": 0.500801,
        "atl_change_percentage": 21010.56452,
        "atl_date": "2020-05-11T19:35:23.449Z",
        "roi": null,
        "last_updated": "2025-04-07T14:56:25.982Z"
    },
    {
        "id": "tron",
        "symbol": "trx",
        "name": "TRON",
        "image": "https://coin-images.coingecko.com/coins/images/1094/large/tron-logo.png?1696502193",
        "current_price": 0.228914,
        "market_cap": 21707108171,
        "market_cap_rank": 9,
        "fully_diluted_valuation": 21707113940,
        "total_volume": 1311829157,
        "high_24h": 0.23956,
        "low_24h": 0.221095,
        "price_change_24h": -0.010413132334155584,
        "price_change_percentage_24h": -4.35101,
        "market_cap_change_24h": -1011089086.0867615,
        "market_cap_change_percentage_24h": -4.45057,
        "circulating_supply": 94976247275.91595,
        "total_supply": 94976272520.62297,
        "max_supply": null,
        "ath": 0.431288,
        "ath_change_percentage": -47.74187,
        "ath_date": "2024-12-04T00:10:40.323Z",
        "atl": 0.00180434,
        "atl_change_percentage": 12391.16181,
        "atl_date": "2017-11-12T00:00:00.000Z",
        "roi": {
            "times": 119.48089930594831,
            "currency": "usd",
            "percentage": 11948.089930594831
        },
        "last_updated": "2025-04-07T14:56:28.774Z"
    },
    {
        "id": "cardano",
        "symbol": "ada",
        "name": "Cardano",
        "image": "https://coin-images.coingecko.com/coins/images/975/large/cardano.png?1696502090",
        "current_price": 0.579904,
        "market_cap": 20780702963,
        "market_cap_rank": 10,
        "fully_diluted_valuation": 25978795807,
        "total_volume": 2151549592,
        "high_24h": 0.629761,
        "low_24h": 0.515683,
        "price_change_24h": -0.04876042223817667,
        "price_change_percentage_24h": -7.75619,
        "market_cap_change_24h": -1849149005.5196571,
        "market_cap_change_percentage_24h": -8.17128,
        "circulating_supply": 35995957636.81128,
        "total_supply": 45000000000.0,
        "max_supply": 45000000000.0,
        "ath": 3.09,
        "ath_change_percentage": -81.48642,
        "ath_date": "2021-09-02T06:00:10.474Z",
        "atl": 0.01925275,
        "atl_change_percentage": 2868.39655,
        "atl_date": "2020-03-13T02:22:55.044Z",
        "roi": null,
        "last_updated": "2025-04-07T14:56:24.791Z"
    },
    {
        "id": "the-open-network",
        "symbol": "ton",
        "name": "Toncoin",
        "image": "https://coin-images.coingecko.com/coins/images/17980/large/photo_2024-09-10_17.09.00.jpeg?1725963446",
        "current_price": 3.05,
        "market_cap": 7553589621,
        "market_cap_rank": 15,
        "fully_diluted_valuation": 15657046226,
        "total_volume": 537127725,
        "high_24h": 3.32,
        "low_24h": 2.86,
        "price_change_24h": -0.2586939922790372,
        "price_change_percentage_24h": -7.81106,
        "market_cap_change_24h": -642708038.6736784,
        "market_cap_change_percentage_24h": -7.84144,
        "circulating_supply": 2473293327.220492,
        "total_supply": 5126631164.882575,
        "max_supply": null,
        "ath": 8.25,
        "ath_change_percentage": -63.29622,
        "ath_date": "2024-06-15T00:36:51.509Z",
        "atl": 0.519364,
        "atl_change_percentage": 483.28786,
        "atl_date": "2021-09-21T00:33:11.092Z",
        "roi": null,
        "last_updated": "2025-04-07T14:56:28.728Z"
    },
    {
        "id": "avalanche-2",
        "symbol": "avax",
        "name": "Avalanche",
        "image": "https://coin-images.coingecko.com/coins/images/12559/large/Avalanche_Circle_RedWhite_Trans.png?1696512369",
        "current_price": 16.53,
        "market_cap": 6846927019,
        "market_cap_rank": 18,
        "fully_diluted_valuation": 7451504504,
        "total_volume": 770566288,
        "high_24h": 17.28,
        "low_24h": 14.77,
        "price_change_24h": -0.5711699259528267,
        "price_change_percentage_24h": -3.33923,
        "market_cap_change_24h": -250489236.0273323,
        "market_cap_change_percentage_24h": -3.5293,
        "circulating_supply": 415287350.3920757,
        "total_supply": 451956849.1702163,
        "max_supply": 720000000.0,
        "ath": 144.96,
        "ath_change_percentage": -88.76987,
        "ath_date": "2021-11-21T14:18:56.538Z",
        "atl": 2.8,
        "atl_change_percentage": 481.18381,
        "atl_date": "2020-12-31T13:15:21.540Z",
        "roi": null,
        "last_updated": "2025-04-07T14:56:34.480Z"
    },
    {
        "id": "sui",
        "symbol": "sui",
        "name": "Sui",
        "image": "https://coin-images.coingecko.com/coins/images/26375/large/sui-ocean-square.png?1727791290",
        "current_price": 2.03,
        "market_cap": 6589344069,
        "market_cap_rank": 21,
        "fully_diluted_valuation": 20275011502,
        "total_volume": 2234742588,
        "high_24h": 2.11,
        "low_24h": 1.75,
        "price_change_24h": -0.07737337013162104,
        "price_change_percentage_24h": -3.67306,
        "market_cap_change_24h": -254465692.26656532,
        "market_cap_change_percentage_24h": -3.71819,
        "circulating_supply": 3249982900.458887,
        "total_supply": 10000000000.0,
        "max_supply": 10000000000.0,
        "ath": 5.35,
        "ath_change_percentage": -63.0686,
        "ath_date": "2025-01-04T22:56:18.063Z",
        "atl": 0.364846,
        "atl_change_percentage": 441.20382,
        "atl_date": "2023-10-19T10:40:30.078Z",
        "roi": null,
        "last_updated": "2025-04-07T14:56:27.927Z"
    },
    {
        "id": "hedera-hashgraph",
        "symbol": "hbar",
        "name": "Hedera",
        "image": "https://coin-images.coingecko.com/coins/images/3688/large/hbar.png?1696504364",
        "current_price": 0.145753,
        "market_cap": 6132375046,
        "market_cap_rank": 22,
        "fully_diluted_valuation": 7260976924,
        "total_volume": 562999295,
        "high_24h": 0.155411,
        "low_24h": 0.126032,
        "price_change_24h": -0.009349965795991622,
        "price_change_percentage_24h": -6.02823,
        "market_cap_change_24h": -422577330.83320713,
        "market_cap_change_percentage_24h": -6.44669,
        "circulating_supply": 42228305571.15414,
        "total_supply": 50000000000.0,
        "max_supply": 50000000000.0,
        "ath": 0.569229,
        "ath_change_percentage": -74.85827,
        "ath_date": "2021-09-15T10:40:28.318Z",
        "atl": 0.00986111,
        "atl_change_percentage": 1351.297,
        "atl_date": "2020-01-02T17:30:24.852Z",
        "roi": null,
        "last_updated": "2025-04-07T14:56:28.248Z"
    },
    {
        "id": "mantra-dao",
        "symbol": "om",
        "name": "MANTRA",
        "image": "https://coin-images.coingecko.com/coins/images/12151/large/OM_Token.png?1696511991",
        "current_price": 6.34,
        "market_cap": 6121685672,
        "market_cap_rank": 23,
        "fully_diluted_valuation": 11503340042,
        "total_volume": 228195551,
        "high_24h": 6.41,
        "low_24h": 5.7,
        "price_change_24h": 0.169588,
        "price_change_percentage_24h": 2.74629,
        "market_cap_change_24h": 121247137,
        "market_cap_change_percentage_24h": 2.02064,
        "circulating_supply": 965979039.0699998,
        "total_supply": 1815183914.29,
        "max_supply": null,
        "ath": 8.99,
        "ath_change_percentage": -30.37311,
        "ath_date": "2025-02-23T01:52:21.073Z",
        "atl": 0.01726188,
        "atl_change_percentage": 36143.0451,
        "atl_date": "2023-10-12T17:25:09.068Z",
        "roi": null,
        "last_updated": "2025-04-07T14:56:30.305Z"
    },
    {
        "id": "bitcoin-cash",
        "symbol": "bch",
        "name": "Bitcoin Cash",
        "image": "https://coin-images.coingecko.com/coins/images/780/large/bitcoin-cash-circle.png?1696501932",
        "current_price": 274.75,
        "market_cap": 5436262981,
        "market_cap_rank": 25,
        "fully_diluted_valuation": 5436262981,
        "total_volume": 340361169,
        "high_24h": 295.65,
        "low_24h": 251.09,
        "price_change_24h": -19.94953473547463,
        "price_change_percentage_24h": -6.76947,
        "market_cap_change_24h": -398225646.8207741,
        "market_cap_change_percentage_24h": -6.82537,
        "circulating_supply": 19852753.02165078,
        "total_supply": 19852753.02165078,
        "max_supply": 21000000.0,
        "ath": 3785.82,
        "ath_change_percentage": -92.83886,
        "ath_date": "2017-12-20T00:00:00.000Z",
        "atl": 76.93,
        "atl_change_percentage": 252.38663,
        "atl_date": "2018-12-16T00:00:00.000Z",
        "roi": null,
        "last_updated": "2025-04-07T14:56:34.774Z"
    },
    {
        "id": "litecoin",
        "symbol": "ltc",
        "name": "Litecoin",
        "image": "https://coin-images.coingecko.com/coins/images/2/large/litecoin.png?1696501400",
        "current_price": 71.06,
        "market_cap": 5369360724,
        "market_cap_rank": 26,
        "fully_diluted_valuation": 5369378895,
        "total_volume": 1159490463,
        "high_24h": 79.38,
        "low_24h": 63.71,
        "price_change_24h": -8.192004765849163,
        "price_change_percentage_24h": -10.33621,
        "market_cap_change_24h": -634605344.6839037,
        "market_cap_change_percentage_24h": -10.56977,
        "circulating_supply": 75719839.48347135,
        "total_supply": 75720095.73347135,
        "max_supply": 84000000.0,
        "ath": 410.26,
        "ath_change_percentage": -82.89843,
        "ath_date": "2021-05-10T03:13:07.904Z",
        "atl": 1.15,
        "atl_change_percentage": 6007.0944,
        "atl_date": "2015-01-14T00:00:00.000Z",
        "roi": null,
        "last_updated": "2025-04-07T14:56:31.573Z"
    },
    {
        "id": "pi-network",
        "symbol": "pi",
        "name": "Pi Network",
        "image": "https://coin-images.coingecko.com/coins/images/54342/large/pi_network.jpg?1739347576",
        "current_price": 0.591639,
        "market_cap": 4060430609,
        "market_cap_rank": 31,
        "fully_diluted_valuation": 6246840108,
        "total_volume": 445273043,
        "high_24h": 0.627071,
        "low_24h": 0.537837,
        "price_change_24h": -0.035432030552700944,
        "price_change_percentage_24h": -5.6504,
        "market_cap_change_24h": -232245709.21090984,
        "market_cap_change_percentage_24h": -5.41028,
        "circulating_supply": 6842644150.336463,
        "total_supply": 10527184931.89688,
        "max_supply": 100000000000.0,
        "ath": 2.99,
        "ath_change_percentage": -80.282,
        "ath_date": "2025-02-26T16:41:03.732Z",
        "atl": 0.406999,
        "atl_change_percentage": 44.74173,
        "atl_date": "2025-04-05T04:50:37.033Z",
        "roi": null,
        "last_updated": "2025-04-07T14:56:31.750Z"
    },
    {
        "id": "monero",
        "symbol": "xmr",
        "name": "Monero",
        "image": "https://coin-images.coingecko.com/coins/images/69/large/monero_logo.png?1696501460",
        "current_price": 196.48,
        "market_cap": 3619884009,
        "market_cap_rank": 33,
        "fully_diluted_valuation": 3619884009,
        "total_volume": 107248285,
        "high_24h": 211.6,
        "low_24h": 186.14,
        "price_change_24h": -14.999847970145055,
        "price_change_percentage_24h": -7.09296,
        "market_cap_change_24h": -275242273.3613992,
        "market_cap_change_percentage_24h": -7.06632,
        "circulating_supply": 18446744.07370955,
        "total_supply": 18446744.07370955,
        "max_supply": null,
        "ath": 542.33,
        "ath_change_percentage": -64.06844,
        "ath_date": "2018-01-09T00:00:00.000Z",
        "atl": 0.216177,
        "atl_change_percentage": 90042.01819,
        "atl_date": "2015-01-14T00:00:00.000Z",
        "roi": null,
        "last_updated": "2025-04-07T14:56:31.331Z"
    },
    {
        "id": "hyperliquid",
        "symbol": "hype",
        "name": "Hyperliquid",
        "image": "https://coin-images.coingecko.com/coins/images/50882/large/hyperliquid.jpg?1729431300",
        "current_price": 10.72,
        "market_cap": 3561096408,
        "market_cap_rank": 34,
        "fully_diluted_valuation": 10664155954,
        "total_volume": 266945039,
        "high_24h": 11.43,
        "low_24h": 9.42,
        "price_change_24h": -0.5480252705947031,
        "price_change_percentage_24h": -4.86362,
        "market_cap_change_24h": -212233675.5164976,
        "market_cap_change_percentage_24h": -5.62457,
        "circulating_supply": 333928180.0,
        "total_supply": 999990391.0,
        "max_supply": 1000000000.0,
        "ath": 34.96,
        "ath_change_percentage": -69.73848,
        "ath_date": "2024-12-22T03:56:00.276Z",
        "atl": 3.81,
        "atl_change_percentage": 177.76168,
        "atl_date": "2024-11-29T09:30:30.871Z",
        "roi": null,
        "last_updated": "2025-04-07T14:56:29.062Z"
    },
    {
        "id": "aptos",
        "symbol": "apt",
        "name": "Aptos",
        "image": "https://coin-images.coingecko.com/coins/images/26455/large/aptos_round.png?1696525528",
        "current_price": 4.38,
        "market_cap": 2650079787,
        "market_cap_rank": 41,
        "fully_diluted_valuation": 5024551821,
        "total_volume": 328522961,
        "high_24h": 4.69,
        "low_24h": 3.95,
        "price_change_24h": -0.2941527757007245,
        "price_change_percentage_24h": -6.29689,
        "market_cap_change_24h": -172236891.57189226,
        "market_cap_change_percentage_24h": -6.10268,
        "circulating_supply": 604927663.7196492,
        "total_supply": 1146942974.804205,
        "max_supply": null,
        "ath": 19.92,
        "ath_change_percentage": -78.26832,
        "ath_date": "2023-01-26T14:25:17.390Z",
        "atl": 3.08,
        "atl_change_percentage": 40.56251,
        "atl_date": "2022-12-29T21:35:14.796Z",
        "roi": null,
        "last_updated": "2025-04-07T14:56:34.251Z"
    },
    {
        "id": "near",
        "symbol": "near",
        "name": "NEAR Protocol",
        "image": "https://coin-images.coingecko.com/coins/images/10365/large/near.jpg?1696510367",
        "current_price": 2.15,
        "market_cap": 2567090683,
        "market_cap_rank": 44,
        "fully_diluted_valuation": 2660881112,
        "total_volume": 475755025,
        "high_24h": 2.35,
        "low_24h": 1.99,
        "price_change_24h": -0.20097524525331512,
        "price_change_percentage_24h": -8.56471,
        "market_cap_change_24h": -247310885.6693368,
        "market_cap_change_percentage_24h": -8.78733,
        "circulating_supply": 1200073828.0,
        "total_supply": 1243919353.0,
        "max_supply": null,
        "ath": 20.44,
        "ath_change_percentage": -89.68219,
        "ath_date": "2022-01-16T22:09:45.873Z",
        "atl": 0.526762,
        "atl_change_percentage": 300.32597,
        "atl_date": "2020-11-04T16:09:15.137Z",
        "roi": null,
        "last_updated": "2025-04-07T14:56:30.660Z"
    },
    {
        "id": "crypto-com-chain",
        "symbol": "cro",
        "name": "Cronos",
        "image": "https://coin-images.coingecko.com/coins/images/7310/large/cro_token_logo.png?1696507599",
        "current_price": 0.083044,
        "market_cap": 2274374891,
        "market_cap_rank": 48,
        "fully_diluted_valuation": 8076254420,
        "total_volume": 65945641,
        "high_24h": 0.089436,
        "low_24h": 0.073938,
        "price_change_24h": -0.00604807521917447,
        "price_change_percentage_24h": -6.7886,
        "market_cap_change_24h": -171282893.62647486,
        "market_cap_change_percentage_24h": -7.00355,
        "circulating_supply": 27440459870.86612,
        "total_supply": 97440459870.86612,
        "max_supply": null,
        "ath": 0.965407,
        "ath_change_percentage": -91.49912,
        "ath_date": "2021-11-24T15:53:54.855Z",
        "atl": 0.0121196,
        "atl_change_percentage": 577.15201,
        "atl_date": "2019-02-08T00:00:00.000Z",
        "roi": null,
        "last_updated": "2025-04-07T14:56:27.359Z"
    },
    {
        "id": "internet-computer",
        "symbol": "icp",
        "name": "Internet Computer",
        "image": "https://coin-images.coingecko.com/coins/images/14495/large/Internet_Computer_logo.png?1696514180",
        "current_price": 4.64,
        "market_cap": 2241497158,
        "market_cap_rank": 49,
        "fully_diluted_valuation": 2468316786,
        "total_volume": 149137518,
        "high_24h": 4.95,
        "low_24h": 4.23,
        "price_change_24h": -0.29775659485502803,
        "price_change_percentage_24h": -6.02701,
        "market_cap_change_24h": -135104272.43806934,
        "market_cap_change_percentage_24h": -5.68477,
        "circulating_supply": 483006694.6973145,
        "total_supply": 531882687.4383742,
        "max_supply": null,
        "ath": 700.65,
        "ath_change_percentage": -99.34488,
        "ath_date": "2021-05-10T16:05:53.653Z",
        "atl": 2.87,
        "atl_change_percentage": 60.21051,
        "atl_date": "2023-09-22T00:29:57.369Z",
        "roi": null,
        "last_updated": "2025-04-07T14:56:28.840Z"
    },
    {
        "id": "ethereum-classic",
        "symbol": "etc",
        "name": "Ethereum Classic",
        "image": "https://coin-images.coingecko.com/coins/images/453/large/ethereum-classic-logo.png?1696501717",
        "current_price": 14.48,
        "market_cap": 2185583184,
        "market_cap_rank": 51,
        "fully_diluted_valuation": 2185583184,
        "total_volume": 287061795,
        "high_24h": 15.59,
        "low_24h": 12.88,
        "price_change_24h": -1.1174052799361895,
        "price_change_percentage_24h": -7.16625,
        "market_cap_change_24h": -168061843.8896203,
        "market_cap_change_percentage_24h": -7.14049,
        "circulating_supply": 151428022.1523726,
        "total_supply": 151428022.1523726,
        "max_supply": 210700000.0,
        "ath": 167.09,
        "ath_change_percentage": -91.44718,
        "ath_date": "2021-05-06T18:34:22.133Z",
        "atl": 0.615038,
        "atl_change_percentage": 2223.51552,
        "atl_date": "2016-07-25T00:00:00.000Z",
        "roi": {
            "times": 31.167099432686044,
            "currency": "usd",
            "percentage": 3116.7099432686045
        },
        "last_updated": "2025-04-07T14:56:29.339Z"
    },
    {
        "id": "fasttoken",
        "symbol": "ftn",
        "name": "Fasttoken",
        "image": "https://coin-images.coingecko.com/coins/images/28478/large/lightenicon_200x200.png?1696527472",
        "current_price": 4.05,
        "market_cap": 1742674252,
        "market_cap_rank": 56,
        "fully_diluted_valuation": 3527550499,
        "total_volume": 51066209,
        "high_24h": 4.12,
        "low_24h": 4.0,
        "price_change_24h": 0.01675612,
        "price_change_percentage_24h": 0.41533,
        "market_cap_change_24h": 6928787,
        "market_cap_change_percentage_24h": 0.39918,
        "circulating_supply": 430162637.0,
        "total_supply": 870742437.0,
        "max_supply": 1000000000.0,
        "ath": 4.12,
        "ath_change_percentage": -2.2615,
        "ath_date": "2025-04-07T14:20:34.647Z",
        "atl": 0.398142,
        "atl_change_percentage": 912.55602,
        "atl_date": "2023-01-21T10:15:39.503Z",
        "roi": null,
        "last_updated": "2025-04-07T14:56:25.942Z"
    },
    {
        "id": "vechain",
        "symbol": "vet",
        "name": "VeChain",
        "image": "https://coin-images.coingecko.com/coins/images/1167/large/VET.png?1742383283",
        "current_price": 0.02007185,
        "market_cap": 1718243346,
        "market_cap_rank": 57,
        "fully_diluted_valuation": 1718243346,
        "total_volume": 114560676,
        "high_24h": 0.02130088,
        "low_24h": 0.01791243,
        "price_change_24h": -0.001170344641263994,
        "price_change_percentage_24h": -5.50953,
        "market_cap_change_24h": -108194773.22675967,
        "market_cap_change_percentage_24h": -5.92381,
        "circulating_supply": 85985041177.0,
        "total_supply": 85985041177.0,
        "max_supply": 86712634466.0,
        "ath": 0.280991,
        "ath_change_percentage": -92.939,
        "ath_date": "2021-04-19T01:08:21.675Z",
        "atl": 0.00191713,
        "atl_change_percentage": 934.91859,
        "atl_date": "2020-03-13T02:29:59.652Z",
        "roi": {
            "times": 3.4557175533504796,
            "currency": "eth",
            "percentage": 345.57175533504795
        },
        "last_updated": "2025-04-07T14:56:27.842Z"
    },
    {
        "id": "bittensor",
        "symbol": "tao",
        "name": "Bittensor",
        "image": "https://coin-images.coingecko.com/coins/images/28452/large/ARUsPeNQ_400x400.jpeg?1696527447",
        "current_price": 198.18,
        "market_cap": 1696677771,
        "market_cap_rank": 58,
        "fully_diluted_valuation": 4161954355,
        "total_volume": 276308812,
        "high_24h": 209.0,
        "low_24h": 170.17,
        "price_change_24h": -10.183501724059141,
        "price_change_percentage_24h": -4.88748,
        "market_cap_change_24h": -82436764.9987247,
        "market_cap_change_percentage_24h": -4.63358,
        "circulating_supply": 8560938.0,
        "total_supply": 21000000.0,
        "max_supply": 21000000.0,
        "ath": 757.6,
        "ath_change_percentage": -74.18821,
        "ath_date": "2024-03-07T18:45:36.466Z",
        "atl": 30.83,
        "atl_change_percentage": 534.28999,
        "atl_date": "2023-05-14T08:57:53.732Z",
        "roi": null,
        "last_updated": "2025-04-07T14:56:33.890Z"
    },
    {
        "id": "kaspa",
        "symbol": "kas",
        "name": "Kaspa",
        "image": "https://coin-images.coingecko.com/coins/images/25751/large/kaspa-icon-exchanges.png?1696524837",
        "current_price": 0.064125,
        "market_cap": 1661201437,
        "market_cap_rank": 60,
        "fully_diluted_valuation": 1666609087,
        "total_volume": 254029763,
        "high_24h": 0.066388,
        "low_24h": 0.053016,
        "price_change_24h": 0.00351445,
        "price_change_percentage_24h": 5.79843,
        "market_cap_change_24h": 94091541,
        "market_cap_change_percentage_24h": 6.00414,
        "circulating_supply": 25900045779.39798,
        "total_supply": 25984357281.04186,
        "max_supply": 28704026601.0,
        "ath": 0.207411,
        "ath_change_percentage": -69.39848,
        "ath_date": "2024-08-01T00:40:47.164Z",
        "atl": 0.00017105,
        "atl_change_percentage": 37006.73601,
        "atl_date": "2022-05-26T14:42:59.316Z",
        "roi": null,
        "last_updated": "2025-04-07T14:56:29.805Z"
    },
    {
        "id": "filecoin",
        "symbol": "fil",
        "name": "Filecoin",
        "image": "https://coin-images.coingecko.com/coins/images/12817/large/filecoin.png?1696512609",
        "current_price": 2.39,
        "market_cap": 1547004133,
        "market_cap_rank": 63,
        "fully_diluted_valuation": 4683210669,
        "total_volume": 472324807,
        "high_24h": 2.6,
        "low_24h": 2.14,
        "price_change_24h": -0.19265583761302985,
        "price_change_percentage_24h": -7.44805,
        "market_cap_change_24h": -127255935.37736201,
        "market_cap_change_percentage_24h": -7.60073,
        "circulating_supply": 647306110.0,
        "total_supply": 1959575166.0,
        "max_supply": 1959575166.0,
        "ath": 236.84,
        "ath_change_percentage": -99.00631,
        "ath_date": "2021-04-01T13:29:41.564Z",
        "atl": 2.14,
        "atl_change_percentage": 9.74637,
        "atl_date": "2025-04-07T07:06:32.125Z",
        "roi": null,
        "last_updated": "2025-04-07T14:56:27.327Z"
    },
    {
        "id": "celestia",
        "symbol": "tia",
        "name": "Celestia",
        "image": "https://coin-images.coingecko.com/coins/images/31967/large/tia.jpg?1696530772",
        "current_price": 2.48,
        "market_cap": 1454506322,
        "market_cap_rank": 66,
        "fully_diluted_valuation": 2744344451,
        "total_volume": 179081669,
        "high_24h": 2.55,
        "low_24h": 2.18,
        "price_change_24h": -0.02841114576717496,
        "price_change_percentage_24h": -1.13243,
        "market_cap_change_24h": -21330873.869519472,
        "market_cap_change_percentage_24h": -1.44534,
        "circulating_supply": 590354500.396689,
        "total_supply": 1113873534.246225,
        "max_supply": null,
        "ath": 20.85,
        "ath_change_percentage": -88.19755,
        "ath_date": "2024-02-10T14:30:02.495Z",
        "atl": 2.08,
        "atl_change_percentage": 18.11437,
        "atl_date": "2023-10-31T15:14:31.951Z",
        "roi": null,
        "last_updated": "2025-04-07T14:56:34.890Z"
    },
    {
        "id": "algorand",
        "symbol": "algo",
        "name": "Algorand",
        "image": "https://coin-images.coingecko.com/coins/images/4380/large/download.png?1696504978",
        "current_price": 0.168743,
        "market_cap": 1438256898,
        "market_cap_rank": 67,
        "fully_diluted_valuation": 1438256898,
        "total_volume": 175725905,
        "high_24h": 0.176853,
        "low_24h": 0.148255,
        "price_change_24h": -0.007782690439925688,
        "price_change_percentage_24h": -4.40881,
        "market_cap_change_24h": -72419156.92150307,
        "market_cap_change_percentage_24h": -4.79382,
        "circulating_supply": 8558977860.219485,
        "total_supply": 8558977860.219485,
        "max_supply": 10000000000.0,
        "ath": 3.56,
        "ath_change_percentage": -95.33492,
        "ath_date": "2019-06-20T14:51:19.480Z",
        "atl": 0.087513,
        "atl_change_percentage": 89.83451,
        "atl_date": "2023-09-11T19:42:08.247Z",
        "roi": {
            "times": -0.9296903594408584,
            "currency": "usd",
            "percentage": -92.96903594408583
        },
        "last_updated": "2025-04-07T14:56:34.569Z"
    },
    {
        "id": "sonic-3",
        "symbol": "s",
        "name": "Sonic (prev. FTM)",
        "image": "https://coin-images.coingecko.com/coins/images/38108/large/200x200_Sonic_Logo.png?1734679256",
        "current_price": 0.435528,
        "market_cap": 1378068421,
        "market_cap_rank": 68,
        "fully_diluted_valuation": 1378068421,
        "total_volume": 348890372,
        "high_24h": 0.470713,
        "low_24h": 0.38369,
        "price_change_24h": -0.033329336012051014,
        "price_change_percentage_24h": -7.10863,
        "market_cap_change_24h": -110922977.50738358,
        "market_cap_change_percentage_24h": -7.44954,
        "circulating_supply": 3175000000.0,
        "total_supply": 3175000000.0,
        "max_supply": null,
        "ath": 1.029,
        "ath_change_percentage": -58.04456,
        "ath_date": "2025-01-04T21:35:44.705Z",
        "atl": 0.359647,
        "atl_change_percentage": 20.09537,
        "atl_date": "2025-02-03T02:11:37.229Z",
        "roi": null,
        "last_updated": "2025-04-07T14:56:25.606Z"
    },
    {
        "id": "story-2",
        "symbol": "ip",
        "name": "Story",
        "image": "https://coin-images.coingecko.com/coins/images/54035/large/Transparent_bg.png?1738075331",
        "current_price": 4.25,
        "market_cap": 1106096351,
        "market_cap_rank": 72,
        "fully_diluted_valuation": 4275346376,
        "total_volume": 97155176,
        "high_24h": 4.32,
        "low_24h": 3.85,
        "price_change_24h": 0.087963,
        "price_change_percentage_24h": 2.11509,
        "market_cap_change_24h": 34642936,
        "market_cap_change_percentage_24h": 3.23327,
        "circulating_supply": 259330472.26,
        "total_supply": 1002378855.51,
        "max_supply": null,
        "ath": 7.31,
        "ath_change_percentage": -42.03791,
        "ath_date": "2025-02-26T16:11:25.410Z",
        "atl": 1.0,
        "atl_change_percentage": 323.78309,
        "atl_date": "2025-02-14T03:11:08.309Z",
        "roi": null,
        "last_updated": "2025-04-07T14:56:34.702Z"
    },
    {
        "id": "xdce-crowd-sale",
        "symbol": "xdc",
        "name": "XDC Network",
        "image": "https://coin-images.coingecko.com/coins/images/2912/large/xdc-icon.png?1696503661",
        "current_price": 0.062924,
        "market_cap": 988649978,
        "market_cap_rank": 78,
        "fully_diluted_valuation": 2391861781,
        "total_volume": 75741879,
        "high_24h": 0.068816,
        "low_24h": 0.060147,
        "price_change_24h": -0.00558862693422213,
        "price_change_percentage_24h": -8.15708,
        "market_cap_change_24h": -83779167.87293756,
        "market_cap_change_percentage_24h": -7.81209,
        "circulating_supply": 15700136963.4,
        "total_supply": 37983673103.85,
        "max_supply": null,
        "ath": 0.192754,
        "ath_change_percentage": -67.59973,
        "ath_date": "2021-08-21T04:39:48.324Z",
        "atl": 0.00039532,
        "atl_change_percentage": 15698.13093,
        "atl_date": "2019-07-22T00:00:00.000Z",
        "roi": {
            "times": 4.307140650169859,
            "currency": "eth",
            "percentage": 430.7140650169859
        },
        "last_updated": "2025-04-07T14:56:28.467Z"
    },
    {
        "id": "flare-networks",
        "symbol": "flr",
        "name": "Flare",
        "image": "https://coin-images.coingecko.com/coins/images/28624/large/FLR-icon200x200.png?1696527609",
        "current_price": 0.01186939,
        "market_cap": 745696712,
        "market_cap_rank": 95,
        "fully_diluted_valuation": 1225265949,
        "total_volume": 19747281,
        "high_24h": 0.01303837,
        "low_24h": 0.01093505,
        "price_change_24h": -0.001153996463339541,
        "price_change_percentage_24h": -8.86095,
        "market_cap_change_24h": -56051014.53351581,
        "market_cap_change_percentage_24h": -6.9911,
        "circulating_supply": 62825228597.71117,
        "total_supply": 103229117318.0979,
        "max_supply": null,
        "ath": 0.150073,
        "ath_change_percentage": -92.18085,
        "ath_date": "2023-01-10T03:14:05.921Z",
        "atl": 0.00827405,
        "atl_change_percentage": 41.822,
        "atl_date": "2023-10-19T03:35:41.663Z",
        "roi": null,
        "last_updated": "2025-04-07T14:56:25.906Z"
    },
    {
        "id": "sei-network",
        "symbol": "sei",
        "name": "Sei",
        "image": "https://coin-images.coingecko.com/coins/images/28205/large/Sei_Logo_-_Transparent.png?1696527207",
        "current_price": 0.147982,
        "market_cap": 722531407,
        "market_cap_rank": 97,
        "fully_diluted_valuation": 1479881128,
        "total_volume": 195104957,
        "high_24h": 0.156773,
        "low_24h": 0.132275,
        "price_change_24h": -0.008452904883327228,
        "price_change_percentage_24h": -5.40347,
        "market_cap_change_24h": -40498606.26436591,
        "market_cap_change_percentage_24h": -5.3076,
        "circulating_supply": 4882361111.0,
        "total_supply": 10000000000.0,
        "max_supply": null,
        "ath": 1.14,
        "ath_change_percentage": -87.15552,
        "ath_date": "2024-03-16T02:30:23.904Z",
        "atl": 0.095364,
        "atl_change_percentage": 53.50781,
        "atl_date": "2023-10-19T08:05:30.655Z",
        "roi": null,
        "last_updated": "2025-04-07T14:56:32.572Z"
    },
    {
        "id": "theta-token",
        "symbol": "theta",
        "name": "Theta Network",
        "image": "https://coin-images.coingecko.com/coins/images/2538/large/theta-token-logo.png?1696503349",
        "current_price": 0.714777,
        "market_cap": 712829113,
        "market_cap_rank": 98,
        "fully_diluted_valuation": 712829113,
        "total_volume": 63315966,
        "high_24h": 0.749288,
        "low_24h": 0.637156,
        "price_change_24h": -0.03314915241000527,
        "price_change_percentage_24h": -4.43214,
        "market_cap_change_24h": -34814896.632489085,
        "market_cap_change_percentage_24h": -4.65661,
        "circulating_supply": 1000000000.0,
        "total_supply": 1000000000.0,
        "max_supply": 1000000000.0,
        "ath": 15.72,
        "ath_change_percentage": -95.51957,
        "ath_date": "2021-04-16T13:15:11.190Z",
        "atl": 0.04039979,
        "atl_change_percentage": 1643.35144,
        "atl_date": "2020-03-13T02:24:16.483Z",
        "roi": {
            "times": 3.7651810772108947,
            "currency": "usd",
            "percentage": 376.51810772108945
        },
        "last_updated": "2025-04-07T14:56:28.524Z"
    },
    {
        "id": "injective-protocol",
        "symbol": "inj",
        "name": "Injective",
        "image": "https://coin-images.coingecko.com/coins/images/12882/large/Other_200x200.png?1738782212",
        "current_price": 7.22,
        "market_cap": 703079022,
        "market_cap_rank": 102,
        "fully_diluted_valuation": 719430083,
        "total_volume": 182219323,
        "high_24h": 7.94,
        "low_24h": 6.41,
        "price_change_24h": -0.6990832411733354,
        "price_change_percentage_24h": -8.82736,
        "market_cap_change_24h": -69948979.1682893,
        "market_cap_change_percentage_24h": -9.0487,
        "circulating_supply": 97727220.33,
        "total_supply": 100000000.0,
        "max_supply": null,
        "ath": 52.62,
        "ath_change_percentage": -86.43049,
        "ath_date": "2024-03-14T15:06:22.124Z",
        "atl": 0.657401,
        "atl_change_percentage": 986.15155,
        "atl_date": "2020-11-03T16:19:30.576Z",
        "roi": null,
        "last_updated": "2025-04-07T14:56:31.318Z"
    },
    {
        "id": "tezos",
        "symbol": "xtz",
        "name": "Tezos",
        "image": "https://coin-images.coingecko.com/coins/images/976/large/Tezos-logo.png?1696502091",
        "current_price": 0.589976,
        "market_cap": 611076037,
        "market_cap_rank": 108,
        "fully_diluted_valuation": 622996652,
        "total_volume": 52649481,
        "high_24h": 0.637298,
        "low_24h": 0.533013,
        "price_change_24h": -0.04637177222899724,
        "price_change_percentage_24h": -7.28717,
        "market_cap_change_24h": -48912130.46081531,
        "market_cap_change_percentage_24h": -7.41106,
        "circulating_supply": 1038105809.528222,
        "total_supply": 1058356742.482988,
        "max_supply": null,
        "ath": 9.12,
        "ath_change_percentage": -93.58439,
        "ath_date": "2021-10-04T00:41:18.025Z",
        "atl": 0.350476,
        "atl_change_percentage": 66.87332,
        "atl_date": "2018-12-07T00:00:00.000Z",
        "roi": {
            "times": 0.2552680471432166,
            "currency": "usd",
            "percentage": 25.52680471432166
        },
        "last_updated": "2025-04-07T14:56:27.645Z"
    },
    {
        "id": "gala",
        "symbol": "gala",
        "name": "GALA",
        "image": "https://coin-images.coingecko.com/coins/images/12493/large/GALA_token_image_-_200PNG.png?1709725869",
        "current_price": 0.01355757,
        "market_cap": 593458746,
        "market_cap_rank": 111,
        "fully_diluted_valuation": 593458746,
        "total_volume": 180156933,
        "high_24h": 0.01427014,
        "low_24h": 0.0118267,
        "price_change_24h": -0.000684003187622205,
        "price_change_percentage_24h": -4.80286,
        "market_cap_change_24h": -31410059.112030864,
        "market_cap_change_percentage_24h": -5.02666,
        "circulating_supply": 43881712483.37638,
        "total_supply": 43881712483.37638,
        "max_supply": 50000000000.0,
        "ath": 0.824837,
        "ath_change_percentage": -98.37956,
        "ath_date": "2021-11-26T01:03:48.731Z",
        "atl": 0.00013475,
        "atl_change_percentage": 9819.14165,
        "atl_date": "2020-12-28T08:46:48.367Z",
        "roi": null,
        "last_updated": "2025-04-07T14:56:27.919Z"
    },
    {
        "id": "kaia",
        "symbol": "kaia",
        "name": "Kaia",
        "image": "https://coin-images.coingecko.com/coins/images/39901/large/KAIA.png?1724734368",
        "current_price": 0.098206,
        "market_cap": 573750784,
        "market_cap_rank": 113,
        "fully_diluted_valuation": 573750803,
        "total_volume": 60105743,
        "high_24h": 0.104841,
        "low_24h": 0.090737,
        "price_change_24h": -0.006615048406239138,
        "price_change_percentage_24h": -6.31078,
        "market_cap_change_24h": -40172434.95856917,
        "market_cap_change_percentage_24h": -6.54356,
        "circulating_supply": 5856641747.106198,
        "total_supply": 5856641936.044253,
        "max_supply": null,
        "ath": 0.406698,
        "ath_change_percentage": -76.00761,
        "ath_date": "2024-12-03T00:11:32.242Z",
        "atl": 0.090737,
        "atl_change_percentage": 7.53825,
        "atl_date": "2025-04-07T07:06:20.797Z",
        "roi": null,
        "last_updated": "2025-04-07T14:56:28.959Z"
    },
    {
        "id": "iota",
        "symbol": "iota",
        "name": "IOTA",
        "image": "https://coin-images.coingecko.com/coins/images/692/large/IOTA_Thumbnail_%281%29.png?1743772896",
        "current_price": 0.150785,
        "market_cap": 556977867,
        "market_cap_rank": 116,
        "fully_diluted_valuation": 690974628,
        "total_volume": 75600786,
        "high_24h": 0.15826,
        "low_24h": 0.132462,
        "price_change_24h": -0.007367890482680967,
        "price_change_percentage_24h": -4.65871,
        "market_cap_change_24h": -29568677.223944664,
        "market_cap_change_percentage_24h": -5.04115,
        "circulating_supply": 3707948285.0,
        "total_supply": 4600000000.0,
        "max_supply": null,
        "ath": 5.25,
        "ath_change_percentage": -97.17653,
        "ath_date": "2017-12-19T00:00:00.000Z",
        "atl": 0.081637,
        "atl_change_percentage": 81.532,
        "atl_date": "2020-03-13T02:22:41.168Z",
        "roi": {
            "times": 0.41800013897998356,
            "currency": "btc",
            "percentage": 41.80001389799836
        },
        "last_updated": "2025-04-07T14:56:30.224Z"
    },
    {
        "id": "flow",
        "symbol": "flow",
        "name": "Flow",
        "image": "https://coin-images.coingecko.com/coins/images/13446/large/5f6294c0c7a8cda55cb1c936_Flow_Wordmark.png?1696513210",
        "current_price": 0.331414,
        "market_cap": 520255273,
        "market_cap_rank": 119,
        "fully_diluted_valuation": 520255273,
        "total_volume": 60732482,
        "high_24h": 0.362139,
        "low_24h": 0.306654,
        "price_change_24h": -0.029927972340647313,
        "price_change_percentage_24h": -8.28246,
        "market_cap_change_24h": -47934700.01230949,
        "market_cap_change_percentage_24h": -8.43639,
        "circulating_supply": 1574016688.191111,
        "total_supply": 1574016688.191111,
        "max_supply": null,
        "ath": 42.4,
        "ath_change_percentage": -99.22842,
        "ath_date": "2021-04-05T13:49:10.098Z",
        "atl": 0.306654,
        "atl_change_percentage": 6.67682,
        "atl_date": "2025-04-07T07:05:50.217Z",
        "roi": null,
        "last_updated": "2025-04-07T14:56:25.777Z"
    },
    {
        "id": "zcash",
        "symbol": "zec",
        "name": "Zcash",
        "image": "https://coin-images.coingecko.com/coins/images/486/large/circle-zcash-color.png?1696501740",
        "current_price": 30.98,
        "market_cap": 497574975,
        "market_cap_rank": 123,
        "fully_diluted_valuation": 497626417,
        "total_volume": 114454501,
        "high_24h": 38.48,
        "low_24h": 28.16,
        "price_change_24h": -7.3281698246223,
        "price_change_percentage_24h": -19.12956,
        "market_cap_change_24h": -113716108.68595147,
        "market_cap_change_percentage_24h": -18.60261,
        "circulating_supply": 15990023.6030448,
        "total_supply": 15991676.7280448,
        "max_supply": 21000000.0,
        "ath": 3191.93,
        "ath_change_percentage": -99.03295,
        "ath_date": "2016-10-29T00:00:00.000Z",
        "atl": 16.08,
        "atl_change_percentage": 91.96093,
        "atl_date": "2024-07-05T04:22:29.321Z",
        "roi": null,
        "last_updated": "2025-04-07T14:56:29.581Z"
    },
    {
        "id": "berachain-bera",
        "symbol": "bera",
        "name": "Berachain",
        "image": "https://coin-images.coingecko.com/coins/images/25235/large/BERA.png?1738822008",
        "current_price": 4.51,
        "market_cap": 487391448,
        "market_cap_rank": 131,
        "fully_diluted_valuation": 2258964146,
        "total_volume": 312867663,
        "high_24h": 5.56,
        "low_24h": 4.14,
        "price_change_24h": -1.01773700138523,
        "price_change_percentage_24h": -18.41187,
        "market_cap_change_24h": -108803242.99928492,
        "market_cap_change_percentage_24h": -18.24962,
        "circulating_supply": 107989297.5953384,
        "total_supply": 500509297.5953384,
        "max_supply": null,
        "ath": 14.83,
        "ath_change_percentage": -70.0176,
        "ath_date": "2025-02-06T14:16:01.862Z",
        "atl": 4.14,
        "atl_change_percentage": 7.39809,
        "atl_date": "2025-04-07T08:02:39.754Z",
        "roi": null,
        "last_updated": "2025-04-07T14:56:34.171Z"
    },
    {
        "id": "kava",
        "symbol": "kava",
        "name": "Kava",
        "image": "https://coin-images.coingecko.com/coins/images/9761/large/kava.png?1696509822",
        "current_price": 0.425919,
        "market_cap": 460684679,
        "market_cap_rank": 136,
        "fully_diluted_valuation": 460684679,
        "total_volume": 40414620,
        "high_24h": 0.433833,
        "low_24h": 0.39362,
        "price_change_24h": 0.02397867,
        "price_change_percentage_24h": 5.96573,
        "market_cap_change_24h": 25960305,
        "market_cap_change_percentage_24h": 5.97167,
        "circulating_supply": 1082853469.0,
        "total_supply": 1082853469.0,
        "max_supply": null,
        "ath": 9.12,
        "ath_change_percentage": -95.40291,
        "ath_date": "2021-08-30T11:10:02.948Z",
        "atl": 0.247359,
        "atl_change_percentage": 69.49669,
        "atl_date": "2024-08-05T06:27:34.050Z",
        "roi": null,
        "last_updated": "2025-04-07T14:56:29.264Z"
    },
    {
        "id": "coredaoorg",
        "symbol": "core",
        "name": "Core",
        "image": "https://coin-images.coingecko.com/coins/images/28938/large/file_589.jpg?1701868471",
        "current_price": 0.426715,
        "market_cap": 426101586,
        "market_cap_rank": 145,
        "fully_diluted_valuation": 896101690,
        "total_volume": 40702426,
        "high_24h": 0.432308,
        "low_24h": 0.37907,
        "price_change_24h": 0.00713609,
        "price_change_percentage_24h": 1.70078,
        "market_cap_change_24h": 5996863,
        "market_cap_change_percentage_24h": 1.42747,
        "circulating_supply": 998562261.9237388,
        "total_supply": 2100000000.0,
        "max_supply": 2100000000.0,
        "ath": 6.14,
        "ath_change_percentage": -93.13542,
        "ath_date": "2023-02-08T12:55:39.828Z",
        "atl": 0.334237,
        "atl_change_percentage": 26.17832,
        "atl_date": "2023-11-03T01:20:55.441Z",
        "roi": null,
        "last_updated": "2025-04-07T14:56:24.538Z"
    },
    {
        "id": "dydx-chain",
        "symbol": "dydx",
        "name": "dYdX",
        "image": "https://coin-images.coingecko.com/coins/images/32594/large/dydx.png?1698673495",
        "current_price": 0.548671,
        "market_cap": 421852523,
        "market_cap_rank": 146,
        "fully_diluted_valuation": 480807867,
        "total_volume": 47031424,
        "high_24h": 0.586929,
        "low_24h": 0.50401,
        "price_change_24h": -0.03551806657333456,
        "price_change_percentage_24h": -6.07989,
        "market_cap_change_24h": -29605178.977161825,
        "market_cap_change_percentage_24h": -6.55769,
        "circulating_supply": 773125071.0143969,
        "total_supply": 881171965.194378,
        "max_supply": 1000000000.0,
        "ath": 4.52,
        "ath_change_percentage": -87.88389,
        "ath_date": "2024-03-07T22:19:11.131Z",
        "atl": 0.50401,
        "atl_change_percentage": 8.6259,
        "atl_date": "2025-04-07T07:05:30.244Z",
        "roi": null,
        "last_updated": "2025-04-07T14:56:25.251Z"
    },
    {
        "id": "chiliz",
        "symbol": "chz",
        "name": "Chiliz",
        "image": "https://coin-images.coingecko.com/coins/images/8834/large/CHZ_Token_updated.png?1696508986",
        "current_price": 0.03930058,
        "market_cap": 372960237,
        "market_cap_rank": 162,
        "fully_diluted_valuation": 372960237,
        "total_volume": 83933978,
        "high_24h": 0.04059969,
        "low_24h": 0.03589692,
        "price_change_24h": -0.001218908662833584,
        "price_change_percentage_24h": -3.0082,
        "market_cap_change_24h": -12219673.015187085,
        "market_cap_change_percentage_24h": -3.17246,
        "circulating_supply": 9514988756.0,
        "total_supply": 9514988756.0,
        "max_supply": null,
        "ath": 0.878633,
        "ath_change_percentage": -95.57302,
        "ath_date": "2021-03-13T08:04:21.200Z",
        "atl": 0.00410887,
        "atl_change_percentage": 846.65689,
        "atl_date": "2019-09-28T00:00:00.000Z",
        "roi": {
            "times": 0.7863901447040932,
            "currency": "usd",
            "percentage": 78.63901447040932
        },
        "last_updated": "2025-04-07T14:56:24.006Z"
    },
    {
        "id": "elrond-erd-2",
        "symbol": "egld",
        "name": "MultiversX",
        "image": "https://coin-images.coingecko.com/coins/images/12335/large/egld-token-logo.png?1696512162",
        "current_price": 13.3,
        "market_cap": 372685886,
        "market_cap_rank": 163,
        "fully_diluted_valuation": 372685886,
        "total_volume": 49022355,
        "high_24h": 13.9,
        "low_24h": 11.91,
        "price_change_24h": -0.4841347382813215,
        "price_change_percentage_24h": -3.51214,
        "market_cap_change_24h": -15326434.491722941,
        "market_cap_change_percentage_24h": -3.94999,
        "circulating_supply": 28101493.0,
        "total_supply": 28101493.0,
        "max_supply": 31415926.0,
        "ath": 545.64,
        "ath_change_percentage": -97.59002,
        "ath_date": "2021-11-23T10:33:26.737Z",
        "atl": 6.51,
        "atl_change_percentage": 102.09746,
        "atl_date": "2020-10-07T01:44:53.554Z",
        "roi": null,
        "last_updated": "2025-04-07T14:56:25.371Z"
    },
    {
        "id": "ronin",
        "symbol": "ron",
        "name": "Ronin",
        "image": "https://coin-images.coingecko.com/coins/images/20009/large/photo_2024-04-06_22-52-24.jpg?1712415367",
        "current_price": 0.564408,
        "market_cap": 350197876,
        "market_cap_rank": 173,
        "fully_diluted_valuation": 565391831,
        "total_volume": 47997780,
        "high_24h": 0.626904,
        "low_24h": 0.517512,
        "price_change_24h": -0.06206224295827345,
        "price_change_percentage_24h": -9.90665,
        "market_cap_change_24h": -37491395.403868794,
        "market_cap_change_percentage_24h": -9.67048,
        "circulating_supply": 619389698.9641546,
        "total_supply": 1000000000.0,
        "max_supply": 1000000000.0,
        "ath": 4.45,
        "ath_change_percentage": -87.42308,
        "ath_date": "2024-03-26T05:12:38.487Z",
        "atl": 0.196601,
        "atl_change_percentage": 184.71476,
        "atl_date": "2022-11-21T19:36:31.487Z",
        "roi": null,
        "last_updated": "2025-04-07T14:56:32.786Z"
    },
    {
        "id": "ecash",
        "symbol": "xec",
        "name": "eCash",
        "image": "https://coin-images.coingecko.com/coins/images/16646/large/Logo_final-22.png?1696516207",
        "current_price": 1.758e-05,
        "market_cap": 348793387,
        "market_cap_rank": 174,
        "fully_diluted_valuation": 348801350,
        "total_volume": 37700352,
        "high_24h": 1.878e-05,
        "low_24h": 1.604e-05,
        "price_change_24h": -1.151832740349e-06,
        "price_change_percentage_24h": -6.14996,
        "market_cap_change_24h": -23247621.664536834,
        "market_cap_change_percentage_24h": -6.24867,
        "circulating_supply": 19847760922583.0,
        "total_supply": 19848214047583.0,
        "max_supply": 21000000000000.0,
        "ath": 0.00038001,
        "ath_change_percentage": -95.42326,
        "ath_date": "2021-09-04T17:09:31.137Z",
        "atl": 1.604e-05,
        "atl_change_percentage": 8.4323,
        "atl_date": "2025-04-07T07:05:49.124Z",
        "roi": null,
        "last_updated": "2025-04-07T14:56:25.193Z"
    },
    {
        "id": "arweave",
        "symbol": "ar",
        "name": "Arweave",
        "image": "https://coin-images.coingecko.com/coins/images/4343/large/oRt6SiEN_400x400.jpg?1696504946",
        "current_price": 5.19,
        "market_cap": 339200338,
        "market_cap_rank": 179,
        "fully_diluted_valuation": 339200338,
        "total_volume": 90321274,
        "high_24h": 5.48,
        "low_24h": 4.68,
        "price_change_24h": -0.25994369724688227,
        "price_change_percentage_24h": -4.76672,
        "market_cap_change_24h": -18186356.895492673,
        "market_cap_change_percentage_24h": -5.08871,
        "circulating_supply": 65454185.5381511,
        "total_supply": 65454185.5381511,
        "max_supply": 66000000.0,
        "ath": 89.24,
        "ath_change_percentage": -94.22962,
        "ath_date": "2021-11-05T04:14:42.689Z",
        "atl": 0.298788,
        "atl_change_percentage": 1623.36643,
        "atl_date": "2020-01-31T06:47:36.543Z",
        "roi": {
            "times": 6.018056995958317,
            "currency": "usd",
            "percentage": 601.8056995958318
        },
        "last_updated": "2025-04-07T14:56:34.093Z"
    },
    {
        "id": "plume",
        "symbol": "plume",
        "name": "Plume",
        "image": "https://coin-images.coingecko.com/coins/images/53623/large/plume-token.png?1736896935",
        "current_price": 0.15103,
        "market_cap": 301596639,
        "market_cap_rank": 193,
        "fully_diluted_valuation": 1507983196,
        "total_volume": 89656482,
        "high_24h": 0.168811,
        "low_24h": 0.132633,
        "price_change_24h": -0.01573118452246819,
        "price_change_percentage_24h": -9.43335,
        "market_cap_change_24h": -32086392.030686975,
        "market_cap_change_percentage_24h": -9.61583,
        "circulating_supply": 2000000000.0,
        "total_supply": 10000000000.0,
        "max_supply": 10000000000.0,
        "ath": 0.247537,
        "ath_change_percentage": -40.36721,
        "ath_date": "2025-03-19T22:25:55.148Z",
        "atl": 0.084391,
        "atl_change_percentage": 74.91579,
        "atl_date": "2025-01-21T10:41:07.928Z",
        "roi": null,
        "last_updated": "2025-04-07T14:56:31.759Z"
    },
    {
        "id": "chain-2",
        "symbol": "xcn",
        "name": "Onyxcoin",
        "image": "https://coin-images.coingecko.com/coins/images/24210/large/onyxlogo.jpg?1696523397",
        "current_price": 0.00884614,
        "market_cap": 293782447,
        "market_cap_rank": 196,
        "fully_diluted_valuation": 428388590,
        "total_volume": 52095420,
        "high_24h": 0.00945324,
        "low_24h": 0.00762499,
        "price_change_24h": -0.00054522775490728,
        "price_change_percentage_24h": -5.80562,
        "market_cap_change_24h": -17038583.302080035,
        "market_cap_change_percentage_24h": -5.4818,
        "circulating_supply": 33193662951.2519,
        "total_supply": 48402437326.51888,
        "max_supply": 48402437326.51888,
        "ath": 0.184139,
        "ath_change_percentage": -95.25368,
        "ath_date": "2022-05-27T11:45:24.820Z",
        "atl": 0.0007055,
        "atl_change_percentage": 1138.81165,
        "atl_date": "2023-10-11T20:12:02.910Z",
        "roi": null,
        "last_updated": "2025-04-07T14:56:33.081Z"
    },
    {
        "id": "gnosis",
        "symbol": "gno",
        "name": "Gnosis",
        "image": "https://coin-images.coingecko.com/coins/images/662/large/logo_square_simple_300px.png?1696501854",
        "current_price": 100.06,
        "market_cap": 258881612,
        "market_cap_rank": 205,
        "fully_diluted_valuation": 299910463,
        "total_volume": 55576110,
        "high_24h": 113.73,
        "low_24h": 92.96,
        "price_change_24h": -13.377244382847934,
        "price_change_percentage_24h": -11.79241,
        "market_cap_change_24h": -34489880.397073984,
        "market_cap_change_percentage_24h": -11.75638,
        "circulating_supply": 2589589.0,
        "total_supply": 3000000.0,
        "max_supply": 3000000.0,
        "ath": 644.2,
        "ath_change_percentage": -84.55948,
        "ath_date": "2021-11-08T17:33:29.302Z",
        "atl": 6.88,
        "atl_change_percentage": 1344.89772,
        "atl_date": "2020-03-13T02:24:11.825Z",
        "roi": null,
        "last_updated": "2025-04-07T14:56:27.107Z"
    },
    {
        "id": "aioz-network",
        "symbol": "aioz",
        "name": "AIOZ Network",
        "image": "https://coin-images.coingecko.com/coins/images/14631/large/aioz-logo-200.png?1696514309",
        "current_price": 0.202969,
        "market_cap": 236187287,
        "market_cap_rank": 219,
        "fully_diluted_valuation": 236476290,
        "total_volume": 22577982,
        "high_24h": 0.21646,
        "low_24h": 0.176337,
        "price_change_24h": -0.013312684408575581,
        "price_change_percentage_24h": -6.15526,
        "market_cap_change_24h": -15730050.326881558,
        "market_cap_change_percentage_24h": -6.24413,
        "circulating_supply": 1166600172.747093,
        "total_supply": 1168027642.085023,
        "max_supply": null,
        "ath": 2.65,
        "ath_change_percentage": -92.48886,
        "ath_date": "2021-04-03T11:55:34.211Z",
        "atl": 0.01099588,
        "atl_change_percentage": 1710.79574,
        "atl_date": "2023-09-13T19:20:42.446Z",
        "roi": null,
        "last_updated": "2025-04-07T14:56:32.575Z"
    },
    {
        "id": "wemix-token",
        "symbol": "wemix",
        "name": "WEMIX",
        "image": "https://coin-images.coingecko.com/coins/images/12998/large/wemixcoin_color_200.png?1696512788",
        "current_price": 0.494889,
        "market_cap": 207640749,
        "market_cap_rank": 233,
        "fully_diluted_valuation": 266862519,
        "total_volume": 4337988,
        "high_24h": 0.516611,
        "low_24h": 0.457293,
        "price_change_24h": -0.013134281131298775,
        "price_change_percentage_24h": -2.58537,
        "market_cap_change_24h": -4811821.960758179,
        "market_cap_change_percentage_24h": -2.26489,
        "circulating_supply": 419143127.6551715,
        "total_supply": 538688051.36523,
        "max_supply": 590000000.0,
        "ath": 24.71,
        "ath_change_percentage": -98.00907,
        "ath_date": "2021-11-21T17:33:44.178Z",
        "atl": 0.128398,
        "atl_change_percentage": 283.1783,
        "atl_date": "2021-06-22T12:52:49.089Z",
        "roi": null,
        "last_updated": "2025-04-07T14:56:27.902Z"
    },
    {
        "id": "decred",
        "symbol": "dcr",
        "name": "Decred",
        "image": "https://coin-images.coingecko.com/coins/images/329/large/decred.png?1696501665",
        "current_price": 10.8,
        "market_cap": 180170019,
        "market_cap_rank": 255,
        "fully_diluted_valuation": 180170873,
        "total_volume": 5858563,
        "high_24h": 12.44,
        "low_24h": 10.08,
        "price_change_24h": -1.0406343490363312,
        "price_change_percentage_24h": -8.78686,
        "market_cap_change_24h": -17510986.03949192,
        "market_cap_change_percentage_24h": -8.8582,
        "circulating_supply": 16724297.53653667,
        "total_supply": 16724376.81284239,
        "max_supply": 21000000.0,
        "ath": 247.35,
        "ath_change_percentage": -95.67999,
        "ath_date": "2021-04-17T00:41:14.790Z",
        "atl": 0.43154,
        "atl_change_percentage": 2376.1569,
        "atl_date": "2016-12-26T00:00:00.000Z",
        "roi": null,
        "last_updated": "2025-04-07T14:56:25.033Z"
    },
    {
        "id": "astar",
        "symbol": "astr",
        "name": "Astar",
        "image": "https://coin-images.coingecko.com/coins/images/22617/large/astr.png?1696521933",
        "current_price": 0.02351564,
        "market_cap": 179545232,
        "market_cap_rank": 257,
        "fully_diluted_valuation": 197373034,
        "total_volume": 27986378,
        "high_24h": 0.02604748,
        "low_24h": 0.02112947,
        "price_change_24h": -0.002464259559609897,
        "price_change_percentage_24h": -9.48525,
        "market_cap_change_24h": -18003020.47128147,
        "market_cap_change_percentage_24h": -9.11323,
        "circulating_supply": 7631192052.0,
        "total_supply": 8388925260.0,
        "max_supply": null,
        "ath": 0.421574,
        "ath_change_percentage": -94.50049,
        "ath_date": "2022-01-17T13:34:36.289Z",
        "atl": 0.02112947,
        "atl_change_percentage": 9.72582,
        "atl_date": "2025-04-07T07:01:33.387Z",
        "roi": null,
        "last_updated": "2025-04-07T14:56:33.449Z"
    },
    {
        "id": "aelf",
        "symbol": "elf",
        "name": "aelf",
        "image": "https://coin-images.coingecko.com/coins/images/1371/large/aelf-logo.png?1696502429",
        "current_price": 0.234071,
        "market_cap": 172653597,
        "market_cap_rank": 263,
        "fully_diluted_valuation": 232665771,
        "total_volume": 26167047,
        "high_24h": 0.248521,
        "low_24h": 0.222414,
        "price_change_24h": -0.013941542158573822,
        "price_change_percentage_24h": -5.6213,
        "market_cap_change_24h": -11056135.89177242,
        "market_cap_change_percentage_24h": -6.01826,
        "circulating_supply": 739430347.2303351,
        "total_supply": 996446846.008645,
        "max_supply": 1000000000.0,
        "ath": 2.6,
        "ath_change_percentage": -91.1509,
        "ath_date": "2018-01-09T00:00:00.000Z",
        "atl": 0.03545756,
        "atl_change_percentage": 549.90506,
        "atl_date": "2020-03-13T02:22:35.431Z",
        "roi": null,
        "last_updated": "2025-04-07T14:56:33.103Z"
    },
    {
        "id": "zetachain",
        "symbol": "zeta",
        "name": "ZetaChain",
        "image": "https://coin-images.coingecko.com/coins/images/26718/large/Twitter_icon.png?1696525788",
        "current_price": 0.21895,
        "market_cap": 170947118,
        "market_cap_rank": 267,
        "fully_diluted_valuation": 460076348,
        "total_volume": 63257717,
        "high_24h": 0.228285,
        "low_24h": 0.192313,
        "price_change_24h": -0.007027519573082425,
        "price_change_percentage_24h": -3.10983,
        "market_cap_change_24h": -5259723.6031725705,
        "market_cap_change_percentage_24h": -2.98497,
        "circulating_supply": 780281250.0,
        "total_supply": 2100000000.0,
        "max_supply": 2100000000.0,
        "ath": 2.85,
        "ath_change_percentage": -92.45136,
        "ath_date": "2024-02-15T20:45:12.099Z",
        "atl": 0.185893,
        "atl_change_percentage": 15.87313,
        "atl_date": "2025-03-11T01:11:08.089Z",
        "roi": null,
        "last_updated": "2025-04-07T14:56:29.050Z"
    },
    {
        "id": "vethor-token",
        "symbol": "vtho",
        "name": "VeThor",
        "image": "https://coin-images.coingecko.com/coins/images/5230/large/VETHO.png?1742383301",
        "current_price": 0.00190017,
        "market_cap": 166977608,
        "market_cap_rank": 272,
        "fully_diluted_valuation": 167018371,
        "total_volume": 10505088,
        "high_24h": 0.00201752,
        "low_24h": 0.00169428,
        "price_change_24h": -0.000107565977637576,
        "price_change_percentage_24h": -5.35756,
        "market_cap_change_24h": -9630811.932348967,
        "market_cap_change_percentage_24h": -5.4532,
        "circulating_supply": 88102861736.0,
        "total_supply": 88124369407.0,
        "max_supply": null,
        "ath": 0.04671227,
        "ath_change_percentage": -95.97864,
        "ath_date": "2018-08-29T02:40:46.956Z",
        "atl": 0.00015238,
        "atl_change_percentage": 1132.79176,
        "atl_date": "2020-03-16T10:14:24.544Z",
        "roi": null,
        "last_updated": "2025-04-07T14:56:27.859Z"
    },
    {
        "id": "digibyte",
        "symbol": "dgb",
        "name": "DigiByte",
        "image": "https://coin-images.coingecko.com/coins/images/63/large/digibyte.png?1696501454",
        "current_price": 0.00935904,
        "market_cap": 164713085,
        "market_cap_rank": 274,
        "fully_diluted_valuation": 164721238,
        "total_volume": 12236336,
        "high_24h": 0.00956796,
        "low_24h": 0.00859989,
        "price_change_24h": 0.00040927,
        "price_change_percentage_24h": 4.57301,
        "market_cap_change_24h": 7156309,
        "market_cap_change_percentage_24h": 4.54205,
        "circulating_supply": 17624685935.88104,
        "total_supply": 17625558328.36311,
        "max_supply": 21000000000.0,
        "ath": 0.178084,
        "ath_change_percentage": -94.79709,
        "ath_date": "2021-05-01T00:19:01.967Z",
        "atl": 3.099e-05,
        "atl_change_percentage": 29801.80795,
        "atl_date": "2015-01-14T00:00:00.000Z",
        "roi": null,
        "last_updated": "2025-04-07T14:56:25.989Z"
    },
    {
        "id": "vana",
        "symbol": "vana",
        "name": "Vana",
        "image": "https://coin-images.coingecko.com/coins/images/51404/large/logo.png?1731086679",
        "current_price": 5.26,
        "market_cap": 161495898,
        "market_cap_rank": 275,
        "fully_diluted_valuation": 629204798,
        "total_volume": 58814934,
        "high_24h": 5.43,
        "low_24h": 4.69,
        "price_change_24h": -0.015619858884202031,
        "price_change_percentage_24h": -0.29623,
        "market_cap_change_24h": -202116.27743709087,
        "market_cap_change_percentage_24h": -0.125,
        "circulating_supply": 30800000.0,
        "total_supply": 120000000.0,
        "max_supply": 120000000.0,
        "ath": 35.23,
        "ath_change_percentage": -85.16086,
        "ath_date": "2024-12-17T00:40:30.667Z",
        "atl": 4.52,
        "atl_change_percentage": 15.79642,
        "atl_date": "2025-03-11T00:55:50.361Z",
        "roi": null,
        "last_updated": "2025-04-07T14:56:28.076Z"
    },
    {
        "id": "celo",
        "symbol": "celo",
        "name": "Celo",
        "image": "https://coin-images.coingecko.com/coins/images/11090/large/InjXBNx9_400x400.jpg?1696511031",
        "current_price": 0.276024,
        "market_cap": 156476202,
        "market_cap_rank": 281,
        "fully_diluted_valuation": 275506452,
        "total_volume": 41939152,
        "high_24h": 0.296862,
        "low_24h": 0.248403,
        "price_change_24h": -0.02026082476507468,
        "price_change_percentage_24h": -6.8383,
        "market_cap_change_24h": -11682450.21536547,
        "market_cap_change_percentage_24h": -6.94728,
        "circulating_supply": 567958394.0,
        "total_supply": 1000000000.0,
        "max_supply": 1000000000.0,
        "ath": 9.82,
        "ath_change_percentage": -97.22713,
        "ath_date": "2021-08-30T14:25:09.929Z",
        "atl": 0.248403,
        "atl_change_percentage": 9.63318,
        "atl_date": "2025-04-07T06:56:06.791Z",
        "roi": null,
        "last_updated": "2025-04-07T14:56:34.491Z"
    },
    {
        "id": "oasis-network",
        "symbol": "rose",
        "name": "Oasis",
        "image": "https://coin-images.coingecko.com/coins/images/13162/large/200x200_%28Rounded%29.png?1743579893",
        "current_price": 0.02226568,
        "market_cap": 149086274,
        "market_cap_rank": 293,
        "fully_diluted_valuation": 221531643,
        "total_volume": 28502164,
        "high_24h": 0.02313609,
        "low_24h": 0.01952225,
        "price_change_24h": -0.000799826959851927,
        "price_change_percentage_24h": -3.46763,
        "market_cap_change_24h": -6055304.381792873,
        "market_cap_change_percentage_24h": -3.90308,
        "circulating_supply": 6729795897.58809,
        "total_supply": 10000000000.0,
        "max_supply": 10000000000.0,
        "ath": 0.597347,
        "ath_change_percentage": -96.32936,
        "ath_date": "2022-01-15T03:31:11.062Z",
        "atl": 0.01952225,
        "atl_change_percentage": 12.31501,
        "atl_date": "2025-04-07T07:05:43.496Z",
        "roi": null,
        "last_updated": "2025-04-07T14:56:31.039Z"
    },
    {
        "id": "chia",
        "symbol": "xch",
        "name": "Chia",
        "image": "https://coin-images.coingecko.com/coins/images/15174/large/zV5K5y9f_400x400.png?1696514829",
        "current_price": 10.21,
        "market_cap": 148496712,
        "market_cap_rank": 295,
        "fully_diluted_valuation": 336297195,
        "total_volume": 15992237,
        "high_24h": 10.64,
        "low_24h": 8.96,
        "price_change_24h": -0.28003904244274835,
        "price_change_percentage_24h": -2.66883,
        "market_cap_change_24h": -4619095.278363019,
        "market_cap_change_percentage_24h": -3.01673,
        "circulating_supply": 14529394.55235563,
        "total_supply": 32904396.0702661,
        "max_supply": null,
        "ath": 1645.12,
        "ath_change_percentage": -99.38406,
        "ath_date": "2021-05-15T14:24:45.107Z",
        "atl": 8.96,
        "atl_change_percentage": 13.13025,
        "atl_date": "2025-04-07T06:57:27.858Z",
        "roi": null,
        "last_updated": "2025-04-07T14:56:24.141Z"
    },
    {
        "id": "harmony",
        "symbol": "one",
        "name": "Harmony",
        "image": "https://coin-images.coingecko.com/coins/images/4344/large/Y88JAze.png?1696504947",
        "current_price": 0.00958951,
        "market_cap": 138785320,
        "market_cap_rank": 304,
        "fully_diluted_valuation": 139260019,
        "total_volume": 41273094,
        "high_24h": 0.01015777,
        "low_24h": 0.0084838,
        "price_change_24h": -0.000559155957868339,
        "price_change_percentage_24h": -5.50965,
        "market_cap_change_24h": -8693415.490242153,
        "market_cap_change_percentage_24h": -5.89469,
        "circulating_supply": 14518283026.2629,
        "total_supply": 14567941090.26291,
        "max_supply": null,
        "ath": 0.37902,
        "ath_change_percentage": -97.49854,
        "ath_date": "2021-10-26T09:28:49.782Z",
        "atl": 0.00127355,
        "atl_change_percentage": 644.45787,
        "atl_date": "2020-03-13T02:24:14.005Z",
        "roi": {
            "times": 2.0203180131330427,
            "currency": "usd",
            "percentage": 202.03180131330424
        },
        "last_updated": "2025-04-07T14:56:27.901Z"
    },
    {
        "id": "polymesh",
        "symbol": "polyx",
        "name": "Polymesh",
        "image": "https://coin-images.coingecko.com/coins/images/23496/large/Polymesh-symbol.png?1696522706",
        "current_price": 0.11943,
        "market_cap": 137314792,
        "market_cap_rank": 315,
        "fully_diluted_valuation": 137314792,
        "total_volume": 6924753,
        "high_24h": 0.124713,
        "low_24h": 0.105999,
        "price_change_24h": -0.004909332264426469,
        "price_change_percentage_24h": -3.94833,
        "market_cap_change_24h": -6092864.074200809,
        "market_cap_change_percentage_24h": -4.24863,
        "circulating_supply": 1149597123.271117,
        "total_supply": 1149597123.271117,
        "max_supply": null,
        "ath": 0.748771,
        "ath_change_percentage": -84.17291,
        "ath_date": "2024-03-31T21:30:42.403Z",
        "atl": 0.099854,
        "atl_change_percentage": 18.68188,
        "atl_date": "2023-09-11T19:46:51.485Z",
        "roi": null,
        "last_updated": "2025-04-07T14:56:31.723Z"
    },
    {
        "id": "constellation-labs",
        "symbol": "dag",
        "name": "Constellation",
        "image": "https://coin-images.coingecko.com/coins/images/4645/large/Constellation_Network_Logo.png?1696505213",
        "current_price": 0.03488777,
        "market_cap": 123775796,
        "market_cap_rank": 331,
        "fully_diluted_valuation": 123775885,
        "total_volume": 3900197,
        "high_24h": 0.03821619,
        "low_24h": 0.03427412,
        "price_change_24h": -0.003292862339692074,
        "price_change_percentage_24h": -8.62443,
        "market_cap_change_24h": -12731215.484819964,
        "market_cap_change_percentage_24h": -9.32642,
        "circulating_supply": 3549997434.97413,
        "total_supply": 3550000000.0,
        "max_supply": null,
        "ath": 0.451761,
        "ath_change_percentage": -92.29611,
        "ath_date": "2021-08-25T23:30:00.311Z",
        "atl": 0.00110189,
        "atl_change_percentage": 3058.49933,
        "atl_date": "2019-03-09T00:00:00.000Z",
        "roi": {
            "times": -0.6681017215116588,
            "currency": "eth",
            "percentage": -66.81017215116587
        },
        "last_updated": "2025-04-07T14:56:23.844Z"
    },
    {
        "id": "enjincoin",
        "symbol": "enj",
        "name": "Enjin Coin",
        "image": "https://coin-images.coingecko.com/coins/images/1102/large/Symbol_Only_-_Purple.png?1709725966",
        "current_price": 0.066632,
        "market_cap": 121254342,
        "market_cap_rank": 336,
        "fully_diluted_valuation": 125201419,
        "total_volume": 27063602,
        "high_24h": 0.070298,
        "low_24h": 0.059747,
        "price_change_24h": -0.003553126656373695,
        "price_change_percentage_24h": -5.06248,
        "market_cap_change_24h": -6648439.711632922,
        "market_cap_change_percentage_24h": -5.19804,
        "circulating_supply": 1825468607.202291,
        "total_supply": 1884891356.439328,
        "max_supply": null,
        "ath": 4.82,
        "ath_change_percentage": -98.62673,
        "ath_date": "2021-11-25T09:53:41.955Z",
        "atl": 0.01865964,
        "atl_change_percentage": 254.68124,
        "atl_date": "2017-11-12T00:00:00.000Z",
        "roi": null,
        "last_updated": "2025-04-07T14:56:26.425Z"
    },
    {
        "id": "kadena",
        "symbol": "kda",
        "name": "Kadena",
        "image": "https://coin-images.coingecko.com/coins/images/3693/large/Social_-_Profile_Picture.png?1723001308",
        "current_price": 0.370797,
        "market_cap": 115587762,
        "market_cap_rank": 346,
        "fully_diluted_valuation": 115600679,
        "total_volume": 23688609,
        "high_24h": 0.394343,
        "low_24h": 0.326747,
        "price_change_24h": -0.02302761281501009,
        "price_change_percentage_24h": -5.84717,
        "market_cap_change_24h": -7606676.456748426,
        "market_cap_change_percentage_24h": -6.17453,
        "circulating_supply": 312630211.56031,
        "total_supply": 312665146.97838,
        "max_supply": 1000000000.0,
        "ath": 27.64,
        "ath_change_percentage": -98.68499,
        "ath_date": "2021-11-11T13:22:45.731Z",
        "atl": 0.065811,
        "atl_change_percentage": 452.2043,
        "atl_date": "2020-03-13T02:00:28.582Z",
        "roi": {
            "times": -0.6292027229449476,
            "currency": "usd",
            "percentage": -62.92027229449476
        },
        "last_updated": "2025-04-07T14:56:29.974Z"
    },
    {
        "id": "casper-network",
        "symbol": "cspr",
        "name": "Casper Network",
        "image": "https://coin-images.coingecko.com/coins/images/15279/large/Casper_Token_Circle_SU_Red-White_RGB_200_x_200.png?1734587165",
        "current_price": 0.0085383,
        "market_cap": 110918059,
        "market_cap_rank": 358,
        "fully_diluted_valuation": 114836448,
        "total_volume": 9600997,
        "high_24h": 0.00896856,
        "low_24h": 0.007689,
        "price_change_24h": -0.000419195100006662,
        "price_change_percentage_24h": -4.67982,
        "market_cap_change_24h": -5499307.328389689,
        "market_cap_change_percentage_24h": -4.72379,
        "circulating_supply": 12975393736.0,
        "total_supply": 13433773868.0,
        "max_supply": null,
        "ath": 1.33,
        "ath_change_percentage": -99.36088,
        "ath_date": "2021-05-12T00:00:00.000Z",
        "atl": 0.00624854,
        "atl_change_percentage": 35.56999,
        "atl_date": "2024-11-04T21:56:15.653Z",
        "roi": null,
        "last_updated": "2025-04-07T14:56:34.065Z"
    },
    {
        "id": "qubic-network",
        "symbol": "qubic",
        "name": "Qubic",
        "image": "https://coin-images.coingecko.com/coins/images/32949/large/QubicLogo-Token.png?1731185925",
        "current_price": 9.41414e-07,
        "market_cap": 107358829,
        "market_cap_rank": 371,
        "fully_diluted_valuation": 129725313,
        "total_volume": 4973605,
        "high_24h": 9.47874e-07,
        "low_24h": 8.05629e-07,
        "price_change_24h": -8.45670951e-10,
        "price_change_percentage_24h": -0.08975,
        "market_cap_change_24h": -1171920.9658414274,
        "market_cap_change_percentage_24h": -1.07981,
        "circulating_supply": 114925745974641.0,
        "total_supply": 138868675405223.0,
        "max_supply": 200000000000000.0,
        "ath": 1.256e-05,
        "ath_change_percentage": -92.59946,
        "ath_date": "2024-03-02T12:28:41.540Z",
        "atl": 7.03229e-07,
        "atl_change_percentage": 32.19436,
        "atl_date": "2025-03-10T17:12:02.634Z",
        "roi": null,
        "last_updated": "2025-04-07T14:56:31.866Z"
    },
    {
        "id": "skale",
        "symbol": "skl",
        "name": "SKALE",
        "image": "https://coin-images.coingecko.com/coins/images/13245/large/SKALE_token_300x300.png?1696513021",
        "current_price": 0.01855649,
        "market_cap": 106836904,
        "market_cap_rank": 372,
        "fully_diluted_valuation": 112388779,
        "total_volume": 43220406,
        "high_24h": 0.01954396,
        "low_24h": 0.01645324,
        "price_change_24h": -0.000933032745744425,
        "price_change_percentage_24h": -4.78736,
        "market_cap_change_24h": -5722456.492395416,
        "market_cap_change_percentage_24h": -5.08395,
        "circulating_supply": 5775852671.0,
        "total_supply": 6076000000.0,
        "max_supply": 7000000000.0,
        "ath": 1.22,
        "ath_change_percentage": -98.49584,
        "ath_date": "2021-03-12T05:14:18.439Z",
        "atl": 0.01645324,
        "atl_change_percentage": 11.19179,
        "atl_date": "2025-04-07T07:06:36.250Z",
        "roi": null,
        "last_updated": "2025-04-07T14:56:34.473Z"
    },
    {
        "id": "hive",
        "symbol": "hive",
        "name": "Hive",
        "image": "https://coin-images.coingecko.com/coins/images/10840/large/logo_transparent_4x.png?1696510797",
        "current_price": 0.201933,
        "market_cap": 94998389,
        "market_cap_rank": 401,
        "fully_diluted_valuation": null,
        "total_volume": 10486252,
        "high_24h": 0.214511,
        "low_24h": 0.180856,
        "price_change_24h": -0.012387323380338655,
        "price_change_percentage_24h": -5.77982,
        "market_cap_change_24h": -6218539.7789011,
        "market_cap_change_percentage_24h": -6.14377,
        "circulating_supply": 472293946.788,
        "total_supply": null,
        "max_supply": null,
        "ath": 3.41,
        "ath_change_percentage": -94.19122,
        "ath_date": "2021-11-26T01:46:11.175Z",
        "atl": 0.087309,
        "atl_change_percentage": 126.7244,
        "atl_date": "2020-04-06T07:35:48.099Z",
        "roi": null,
        "last_updated": "2025-04-07T14:56:27.893Z"
    },
    {
        "id": "zignaly",
        "symbol": "zig",
        "name": "ZIGChain",
        "image": "https://coin-images.coingecko.com/coins/images/14796/large/zig.jpg?1731990265",
        "current_price": 0.066387,
        "market_cap": 93157805,
        "market_cap_rank": 407,
        "fully_diluted_valuation": 129182630,
        "total_volume": 8138357,
        "high_24h": 0.069018,
        "low_24h": 0.060008,
        "price_change_24h": -0.002497653531291583,
        "price_change_percentage_24h": -3.62584,
        "market_cap_change_24h": -4018022.793446243,
        "market_cap_change_percentage_24h": -4.1348,
        "circulating_supply": 1409333795.2396517,
        "total_supply": 1954333795.2396517,
        "max_supply": 1954333795.2396517,
        "ath": 0.224179,
        "ath_change_percentage": -70.80817,
        "ath_date": "2021-04-15T15:39:42.111Z",
        "atl": 0.00428716,
        "atl_change_percentage": 1426.46453,
        "atl_date": "2023-07-15T05:31:20.452Z",
        "roi": null,
        "last_updated": "2025-04-07T14:56:29.600Z"
    },
    {
        "id": "g-token",
        "symbol": "g",
        "name": "Gravity",
        "image": "https://coin-images.coingecko.com/coins/images/39200/large/gravity.jpg?1721020647",
        "current_price": 0.01275995,
        "market_cap": 92177547,
        "market_cap_rank": 409,
        "fully_diluted_valuation": 152934667,
        "total_volume": 15460982,
        "high_24h": 0.01387649,
        "low_24h": 0.01180325,
        "price_change_24h": -0.001106995343010854,
        "price_change_percentage_24h": -7.98298,
        "market_cap_change_24h": -7940138.660470262,
        "market_cap_change_percentage_24h": -7.93081,
        "circulating_supply": 7232700000.0,
        "total_supply": 12000000000.0,
        "max_supply": 12000000000.0,
        "ath": 0.091691,
        "ath_change_percentage": -86.14125,
        "ath_date": "2024-07-18T08:44:41.666Z",
        "atl": 0.01180325,
        "atl_change_percentage": 7.65909,
        "atl_date": "2025-04-07T07:01:49.313Z",
        "roi": null,
        "last_updated": "2025-04-07T14:56:27.015Z"
    },
    {
        "id": "peaq-2",
        "symbol": "peaq",
        "name": "peaq",
        "image": "https://coin-images.coingecko.com/coins/images/51415/large/peaq-token-brand-icon_%281%29.png?1731122664",
        "current_price": 0.104476,
        "market_cap": 78383979,
        "market_cap_rank": 447,
        "fully_diluted_valuation": 444672669,
        "total_volume": 10320484,
        "high_24h": 0.110702,
        "low_24h": 0.095452,
        "price_change_24h": -0.00575638051780418,
        "price_change_percentage_24h": -5.22206,
        "market_cap_change_24h": -4472766.784570754,
        "market_cap_change_percentage_24h": -5.39819,
        "circulating_supply": 750359848.0262606,
        "total_supply": 4256794810.00079,
        "max_supply": null,
        "ath": 0.750473,
        "ath_change_percentage": -86.16213,
        "ath_date": "2024-12-10T08:55:30.467Z",
        "atl": 0.09477,
        "atl_change_percentage": 9.5802,
        "atl_date": "2025-03-13T22:06:42.802Z",
        "roi": null,
        "last_updated": "2025-04-07T14:56:31.490Z"
    },
    {
        "id": "radix",
        "symbol": "xrd",
        "name": "Radix",
        "image": "https://coin-images.coingecko.com/coins/images/4374/large/6266da240f9ff5b6237a154c_Radix-Icon-256x256.png?1719376420",
        "current_price": 0.0068003,
        "market_cap": 72828226,
        "market_cap_rank": 474,
        "fully_diluted_valuation": 89147756,
        "total_volume": 3754910,
        "high_24h": 0.00747345,
        "low_24h": 0.00631288,
        "price_change_24h": -0.000594238432068002,
        "price_change_percentage_24h": -8.03618,
        "market_cap_change_24h": -6006343.581476301,
        "market_cap_change_percentage_24h": -7.61892,
        "circulating_supply": 10710367015.1508,
        "total_supply": 13110372734.40228,
        "max_supply": 24000000000.0,
        "ath": 0.651264,
        "ath_change_percentage": -98.97028,
        "ath_date": "2021-11-14T16:09:27.130Z",
        "atl": 0.00589431,
        "atl_change_percentage": 13.77398,
        "atl_date": "2025-03-15T12:36:10.085Z",
        "roi": null,
        "last_updated": "2025-04-07T14:56:32.136Z"
    },
    {
        "id": "supra",
        "symbol": "supra",
        "name": "Supra",
        "image": "https://coin-images.coingecko.com/coins/images/35836/large/photo_2024-03-09_19-25-08.jpg?1709983533",
        "current_price": 0.00601575,
        "market_cap": 69826482,
        "market_cap_rank": 487,
        "fully_diluted_valuation": 478884218,
        "total_volume": 5740383,
        "high_24h": 0.00611865,
        "low_24h": 0.00520972,
        "price_change_24h": -9.6080107025946e-05,
        "price_change_percentage_24h": -1.57203,
        "market_cap_change_24h": -1744785.1100672781,
        "market_cap_change_percentage_24h": -2.43783,
        "circulating_supply": 11604199124.82107,
        "total_supply": 79583958287.32724,
        "max_supply": 100000000000.0,
        "ath": 0.072675,
        "ath_change_percentage": -91.78778,
        "ath_date": "2024-12-08T11:50:10.221Z",
        "atl": 0.00520972,
        "atl_change_percentage": 14.5595,
        "atl_date": "2025-04-07T07:05:56.987Z",
        "roi": null,
        "last_updated": "2025-04-07T14:56:34.872Z"
    },
    {
        "id": "ong",
        "symbol": "ong",
        "name": "Ontology Gas",
        "image": "https://coin-images.coingecko.com/coins/images/5716/large/ONG_logo.png?1696506172",
        "current_price": 0.162571,
        "market_cap": 66354460,
        "market_cap_rank": 507,
        "fully_diluted_valuation": 161935325,
        "total_volume": 4119207,
        "high_24h": 0.171643,
        "low_24h": 0.146044,
        "price_change_24h": -0.007284734340841204,
        "price_change_percentage_24h": -4.28878,
        "market_cap_change_24h": -3444331.2748898864,
        "market_cap_change_percentage_24h": -4.93466,
        "circulating_supply": 409759021.4414432,
        "total_supply": 1000000000.0,
        "max_supply": 1000000000.0,
        "ath": 4.39,
        "ath_change_percentage": -96.32662,
        "ath_date": "2018-09-28T10:22:27.611Z",
        "atl": 0.04242318,
        "atl_change_percentage": 279.91301,
        "atl_date": "2020-03-13T02:24:03.119Z",
        "roi": null,
        "last_updated": "2025-04-07T14:56:31.464Z"
    }
]