[
    {
        "date": "2025-03-03",
        "var": -0.18382288767739674
    },
    {
        "date": "2025-03-09",
        "var": -0.01895755274018571
    },
    {
        "date": "2025-03-09",
        "var": -0.01895755274018571
    },
    {
        "date": "2025-03-09",
        "var": -0.230381281715599
    },
    {
        "date": "2025-03-13T10:27:51",
        "var": -0.1815265070846579
    },
    {
        "date": "2025-04-03T20:47:39",
        "var": -0.1815265070846579
    },
    {
        "date": "2025-04-03T21:11:37",
        "var": -0.1815265070846579
    }
]